{
  "imports": {
    "class": "imports",
    "CISCOWAN-SMI": [
      "ciscoWanAgentCapability"
    ],
    "SNMPv2-CONF": [
      "NOTIFICATION-GROUP",
      "MODULE-COMPLIANCE",
      "AGENT-CAPABILITIES"
    ],
    "SNMPv2-SMI": [
      "Unsigned32",
      "iso",
      "Gauge32",
      "Counter64",
      "MibIdentifier",
      "MODULE-IDENTITY",
      "TimeTicks",
      "OBJECT-TYPE",
      "IpAddress",
      "Bits",
      "Counter32",
      "Integer32",
      "NOTIFICATION-TYPE",
      "OBJECT-IDENTITY"
    ],
    "SNMPv2-TC": [
      "DisplayString",
      "TEXTUAL-CONVENTION"
    ]
  },
  "cwVismLapdTrunkCapability": {
    "name": "cwVismLapdTrunkCapability",
    "oid": "1.3.6.1.4.1.351.160.336",
    "class": "moduleidentity",
    "revisions": [
      {
        "revision": "2001-03-15 00:00",
        "description": "Initial version of this MIB module"
      }
    ],
    "lastupdated": "200108220000Z",
    "organization": "Cisco Systems, Inc.",
    "contactinfo": " Cisco Systems Customer Service Postal: 170 W Tasman Drive San Jose, CA 95134 USA Tel: +1 800 553-NETS E-mail: cs-vism@cisco.com",
    "description": "The Agent Capabilities for CISCO-WAN-LAPD-TRUNK-MIB."
  },
  "cwVismLapdTrunkCapabilityV2R00": {
    "name": "cwVismLapdTrunkCapabilityV2R00",
    "oid": "1.3.6.1.4.1.351.160.336.1",
    "class": "agentcapabilities",
    "productrelease": "VISM Release2.2",
    "status": "current",
    "description": "CISCO-WAN-LAPD-TRUNK-MIB Capabilities"
  },
  "meta": {
    "comments": [
      "ASN.1 source file:///Users/neermitt/kusanagi/mibs.snmplabs.com/asn1/CISCO-WAN-VISM-LAPD-TRUNK-CAPABILITY",
      "Produced by pysmi-0.3.4 at Fri May 24 17:25:52 2019",
      "On host NEERMITT-M-J0NV platform Darwin version 18.6.0 by user neermitt",
      "Using Python version 3.7.3 (default, Mar 27 2019, 09:23:15) "
    ],
    "module": "CISCO-WAN-VISM-LAPD-TRUNK-CAPABILITY"
  }
}