{
  "imports": {
    "class": "imports",
    "BRIDGE-MIB": [
      "dot1dBridge"
    ],
    "HOST-RESOURCES-MIB": [
      "hostResourcesMibModule"
    ],
    "IANAifType-MIB": [
      "ianaifType"
    ],
    "IF-MIB": [
      "ifMIB"
    ],
    "INET-ADDRESS-MIB": [
      "inetAddressMIB"
    ],
    "IP-FORWARD-MIB": [
      "ipForward"
    ],
    "IP-MIB": [
      "ipMIB"
    ],
    "OPENBSD-BASE-MIB": [
      "openBSD"
    ],
    "OPENBSD-CARP-MIB": [
      "carpMIBObjects"
    ],
    "OPENBSD-MEM-MIB": [
      "memMIBObjects"
    ],
    "OPENBSD-PF-MIB": [
      "pfMIBObjects"
    ],
    "OPENBSD-SENSORS-MIB": [
      "sensorsMIBObjects"
    ],
    "SNMPv2-CONF": [
      "MODULE-COMPLIANCE",
      "NOTIFICATION-GROUP"
    ],
    "SNMPv2-MIB": [
      "snmpMIB"
    ],
    "SNMPv2-SMI": [
      "iso",
      "OBJECT-IDENTITY",
      "OBJECT-TYPE",
      "Unsigned32",
      "Gauge32",
      "Counter64",
      "NOTIFICATION-TYPE",
      "Integer32",
      "TimeTicks",
      "IpAddress",
      "MODULE-IDENTITY",
      "MibIdentifier",
      "Counter32",
      "Bits"
    ],
    "SNMPv2-TC": [
      "DisplayString",
      "TEXTUAL-CONVENTION"
    ]
  },
  "meta": {
    "comments": [
      "ASN.1 source file:///Users/neermitt/kusanagi/mibs.snmplabs.com/asn1/OPENBSD-SNMPD-CONF",
      "Produced by pysmi-0.3.4 at Fri May 24 20:53:10 2019",
      "On host NEERMITT-M-J0NV platform Darwin version 18.6.0 by user neermitt",
      "Using Python version 3.7.3 (default, Mar 27 2019, 09:23:15) "
    ],
    "module": "OPENBSD-SNMPD-CONF"
  }
}