{
  "imports": {
    "class": "imports",
    "ATM-TC-MIB": [
      "AtmTrafficDescrParamIndex",
      "AtmAddr",
      "AtmConnCastType",
      "AtmVpIdentifier",
      "AtmVcIdentifier",
      "AtmConnKind",
      "AtmServiceCategory"
    ],
    "IF-MIB": [
      "ifIndex",
      "InterfaceIndex"
    ],
    "SNMPv2-CONF": [
      "NOTIFICATION-GROUP",
      "MODULE-COMPLIANCE",
      "OBJECT-GROUP"
    ],
    "SNMPv2-SMI": [
      "Counter64",
      "iso",
      "TimeTicks",
      "MibIdentifier",
      "Bits",
      "OBJECT-IDENTITY",
      "enterprises",
      "MODULE-IDENTITY",
      "Integer32",
      "mib-2",
      "NOTIFICATION-TYPE",
      "Counter32",
      "OBJECT-TYPE",
      "IpAddress",
      "Unsigned32",
      "Gauge32"
    ],
    "SNMPv2-TC": [
      "TruthValue",
      "DisplayString",
      "TEXTUAL-CONVENTION"
    ]
  },
  "rbbProvMIB": {
    "name": "rbbProvMIB",
    "oid": "1.3.6.1.4.1.4839.32",
    "class": "moduleidentity",
    "lastupdated": "9909271200Z",
    "organization": "IETF ADSL MIB Working Group",
    "contactinfo": " Randy Turner Postal: 2Wire, Inc. 694 Tasman Dr. Milpitas, CA 95035 Tel: 408-895-1216 Fax: 408-428-9590 E-mail: rturner@2wire.com",
    "description": "This is the MIB Module for provisioning of broadband customer premises equipment, specifically xDSL-related services. While not precluding other broadband technology, the MIB has been constructed around existing xDSL facilities, including ATM transports."
  },
  "RBBServiceID": {
    "name": "RBBServiceID",
    "class": "textualconvention",
    "type": {
      "type": "OBJECT IDENTIFIER",
      "class": "type"
    },
    "status": "current",
    "description": "A globally unique OID that unambiguously specifies a particular service, and as much protocol and semantics as is necessary to access the service"
  },
  "RBBServiceName": {
    "name": "RBBServiceName",
    "class": "textualconvention",
    "type": {
      "type": "DisplayString",
      "class": "type",
      "constraints": {
        "size": [
          {
            "min": 0,
            "max": 64
          }
        ]
      }
    },
    "status": "current",
    "description": "A string denoting the same information as RBBServiceOID, except this object is in human-readable form."
  },
  "RBBServiceProvider": {
    "name": "RBBServiceProvider",
    "class": "textualconvention",
    "type": {
      "type": "DisplayString",
      "class": "type",
      "constraints": {
        "size": [
          {
            "min": 0,
            "max": 64
          }
        ]
      }
    },
    "status": "current",
    "description": "A human-readable string representing the name of the private or public entity that is making the service available. For a typical internet service provider (ISP), this would be the name of the ISP company itself"
  },
  "RBBServiceStatus": {
    "name": "RBBServiceStatus",
    "class": "textualconvention",
    "type": {
      "type": "INTEGER",
      "class": "type",
      "constraints": {
        "enumeration": {
          "other": 1,
          "up": 2,
          "down": 3,
          "adminDown": 4
        }
      }
    },
    "status": "current",
    "description": "An enumeration representing the current state of a particular service availability or service subscription (i.e., up, down, enabled, etc.)"
  },
  "RBBURLType": {
    "name": "RBBURLType",
    "class": "textualconvention",
    "type": {
      "type": "DisplayString",
      "class": "type",
      "constraints": {
        "size": [
          {
            "min": 0,
            "max": 128
          }
        ]
      }
    },
    "status": "current",
    "description": "An octet string containing a uniform resource locator (URL). The usage of this URL is object- context dependent. See individual object descriptions that reference this textual convention"
  },
  "RBBCPEAuthType": {
    "name": "RBBCPEAuthType",
    "class": "textualconvention",
    "type": {
      "type": "OCTET STRING",
      "class": "type",
      "constraints": {
        "size": [
          {
            "min": 0,
            "max": 64
          }
        ]
      }
    },
    "status": "current",
    "description": "An opaque string used to identify a particular subscriber. Currently, this MIB does not specify how authentication strings are generated. This is still an open issue."
  },
  "RBBMailAddr": {
    "name": "RBBMailAddr",
    "class": "textualconvention",
    "type": {
      "type": "DisplayString",
      "class": "type",
      "constraints": {
        "size": [
          {
            "min": 0,
            "max": 64
          }
        ]
      }
    },
    "status": "current",
    "description": "The email address (user@domain) of a contact that is responsible for some entity that references this textual convention, such as the administrator for an access network, or the email address of the admin for a particular service provider"
  },
  "RBBCPESerialNumber": {
    "name": "RBBCPESerialNumber",
    "class": "textualconvention",
    "type": {
      "type": "DisplayString",
      "class": "type",
      "constraints": {
        "size": [
          {
            "min": 0,
            "max": 32
          }
        ]
      }
    },
    "status": "current",
    "description": "Define the syntax of a product serial number"
  },
  "RBBVendorModel": {
    "name": "RBBVendorModel",
    "class": "textualconvention",
    "type": {
      "type": "DisplayString",
      "class": "type",
      "constraints": {
        "size": [
          {
            "min": 0,
            "max": 64
          }
        ]
      }
    },
    "status": "current",
    "description": "Define the syntax of a CPE vendor model"
  },
  "RowStatus": {
    "name": "RowStatus",
    "class": "textualconvention",
    "type": {
      "type": "INTEGER",
      "class": "type",
      "constraints": {
        "enumeration": {
          "active": 1,
          "notInService": 2,
          "notReady": 3,
          "createAndGo": 4,
          "createAndWait": 5,
          "destroy": 6
        }
      }
    },
    "status": "current"
  },
  "rbbProvMIBObjects": {
    "name": "rbbProvMIBObjects",
    "oid": "1.3.6.1.4.1.4839.32.1",
    "class": "objectidentity"
  },
  "rbbServicesGroup": {
    "name": "rbbServicesGroup",
    "oid": "1.3.6.1.4.1.4839.32.1.1",
    "class": "objectidentity"
  },
  "rbbSubGroup": {
    "name": "rbbSubGroup",
    "oid": "1.3.6.1.4.1.4839.32.1.2",
    "class": "objectidentity"
  },
  "rbbCPEGroup": {
    "name": "rbbCPEGroup",
    "oid": "1.3.6.1.4.1.4839.32.1.3",
    "class": "objectidentity"
  },
  "rbbVendorGroup": {
    "name": "rbbVendorGroup",
    "oid": "1.3.6.1.4.1.4839.32.1.4",
    "class": "objectidentity"
  },
  "rbbNotifyGroup": {
    "name": "rbbNotifyGroup",
    "oid": "1.3.6.1.4.1.4839.32.1.12",
    "class": "objectidentity"
  },
  "srvServicesTable": {
    "name": "srvServicesTable",
    "oid": "1.3.6.1.4.1.4839.32.1.1.1",
    "nodetype": "table",
    "class": "objecttype",
    "maxaccess": "not-accessible",
    "status": "current",
    "description": "This table contains a sequence of rows where each row describes a particular service that is available to a broadband customer. The service availability expressed in this table is assumed to be valid only for customers served by this management infrastructure, and may differ on a regional basis, even within the same overall access network."
  },
  "srvServiceEntry": {
    "name": "srvServiceEntry",
    "oid": "1.3.6.1.4.1.4839.32.1.1.1.1",
    "nodetype": "row",
    "class": "objecttype",
    "maxaccess": "not-accessible",
    "indices": [
      {
        "module": "RBBPROVISIONING-MIB",
        "object": "srvServiceIdentifier",
        "implied": 0
      }
    ],
    "status": "current",
    "description": "This object defines the individual rows in the SRV services table (srvServicesTable)"
  },
  "srvServiceIdentifier": {
    "name": "srvServiceIdentifier",
    "oid": "1.3.6.1.4.1.4839.32.1.1.1.1.1",
    "nodetype": "column",
    "class": "objecttype",
    "syntax": {
      "type": "RBBServiceID",
      "class": "type"
    },
    "maxaccess": "read-create",
    "status": "current",
    "description": "A unique object identifier (OID) value uniquely representing a particular service."
  },
  "srvServiceName": {
    "name": "srvServiceName",
    "oid": "1.3.6.1.4.1.4839.32.1.1.1.1.2",
    "nodetype": "column",
    "class": "objecttype",
    "syntax": {
      "type": "RBBServiceName",
      "class": "type"
    },
    "maxaccess": "read-create",
    "status": "current",
    "description": "A human-readable name string that identifies a service to an end-user"
  },
  "srvServiceProvider": {
    "name": "srvServiceProvider",
    "oid": "1.3.6.1.4.1.4839.32.1.1.1.1.3",
    "nodetype": "column",
    "class": "objecttype",
    "syntax": {
      "type": "RBBServiceProvider",
      "class": "type"
    },
    "maxaccess": "read-create",
    "status": "current",
    "description": "A human-readable name string that identifies the public or private sponsoring entity for a particular service."
  },
  "srvServiceStatus": {
    "name": "srvServiceStatus",
    "oid": "1.3.6.1.4.1.4839.32.1.1.1.1.4",
    "nodetype": "column",
    "class": "objecttype",
    "syntax": {
      "type": "RBBServiceStatus",
      "class": "type"
    },
    "maxaccess": "read-create",
    "status": "current",
    "description": "An INTEGER enumeration describing the current availability status of a particular service. NOTE: This status implies different semantics than that used by srvServiceSubrStatus"
  },
  "srvServiceConnType": {
    "name": "srvServiceConnType",
    "oid": "1.3.6.1.4.1.4839.32.1.1.1.1.5",
    "nodetype": "column",
    "class": "objecttype",
    "syntax": {
      "type": "AtmConnKind",
      "class": "type"
    },
    "maxaccess": "read-create",
    "status": "current",
    "description": "An enumerated value describing the type of endpoint address used to refer to a particular service, as well as whether the CPE should be an initiator or target during the connection."
  },
  "srvServiceQOSType": {
    "name": "srvServiceQOSType",
    "oid": "1.3.6.1.4.1.4839.32.1.1.1.1.6",
    "nodetype": "column",
    "class": "objecttype",
    "syntax": {
      "type": "INTEGER",
      "class": "type"
    },
    "maxaccess": "read-create",
    "status": "current",
    "description": "The quality-of-service to be associated with a connection to a particular service."
  },
  "srvServiceSpeedReq": {
    "name": "srvServiceSpeedReq",
    "oid": "1.3.6.1.4.1.4839.32.1.1.1.1.7",
    "nodetype": "column",
    "class": "objecttype",
    "syntax": {
      "type": "INTEGER",
      "class": "type"
    },
    "maxaccess": "read-create",
    "status": "current",
    "description": "The bandwidth or speed (in bits-per-second) necessary to realize a particular service"
  },
  "srvServiceLatencyReq": {
    "name": "srvServiceLatencyReq",
    "oid": "1.3.6.1.4.1.4839.32.1.1.1.1.8",
    "nodetype": "column",
    "class": "objecttype",
    "syntax": {
      "type": "INTEGER",
      "class": "type",
      "constraints": {
        "enumeration": {
          "high": 1,
          "med": 2,
          "low": 3
        }
      }
    },
    "maxaccess": "read-create",
    "status": "current",
    "description": "An enumerated value that describes whether or not a particular service has special latency requirements associated to effectively realize the service."
  },
  "srvServiceURL": {
    "name": "srvServiceURL",
    "oid": "1.3.6.1.4.1.4839.32.1.1.1.1.9",
    "nodetype": "column",
    "class": "objecttype",
    "syntax": {
      "type": "RBBURLType",
      "class": "type"
    },
    "maxaccess": "read-create",
    "status": "current",
    "description": "A URL string associated with a particular service. A service may be provisioned with an associated URL that can be used either as a provisioning link or as a potentially advertising source for the service."
  },
  "srvServiceDescr": {
    "name": "srvServiceDescr",
    "oid": "1.3.6.1.4.1.4839.32.1.1.1.1.10",
    "nodetype": "column",
    "class": "objecttype",
    "syntax": {
      "type": "DisplayString",
      "class": "type",
      "constraints": {
        "size": [
          {
            "min": 0,
            "max": 256
          }
        ]
      }
    },
    "maxaccess": "read-create",
    "status": "current",
    "description": "A human-readable string used to provide a brief description for a particular service."
  },
  "srvAdminContact": {
    "name": "srvAdminContact",
    "oid": "1.3.6.1.4.1.4839.32.1.1.1.1.11",
    "nodetype": "column",
    "class": "objecttype",
    "syntax": {
      "type": "RBBMailAddr",
      "class": "type"
    },
    "maxaccess": "read-create",
    "status": "current",
    "description": "A string representing the email address of an administrator contact for the particular service. This could either be a contact used to request new service or options associated with the service, OR, could be used as a support contact address for an existing subscription."
  },
  "srvRowInfo": {
    "name": "srvRowInfo",
    "oid": "1.3.6.1.4.1.4839.32.1.1.1.1.12",
    "nodetype": "column",
    "class": "objecttype",
    "syntax": {
      "type": "RowStatus",
      "class": "type"
    },
    "maxaccess": "read-create",
    "status": "current",
    "description": "Maintains row status information for this table"
  },
  "rbbSubTable": {
    "name": "rbbSubTable",
    "oid": "1.3.6.1.4.1.4839.32.1.2.1",
    "nodetype": "table",
    "class": "objecttype",
    "maxaccess": "not-accessible",
    "status": "current",
    "description": "This table contains a sequence of rows where each row describes a particular service subscription between an end-user CPE and a particular service."
  },
  "rbbSubEntry": {
    "name": "rbbSubEntry",
    "oid": "1.3.6.1.4.1.4839.32.1.2.1.1",
    "nodetype": "row",
    "class": "objecttype",
    "maxaccess": "not-accessible",
    "indices": [
      {
        "module": "RBBPROVISIONING-MIB",
        "object": "rbbSubVendor",
        "implied": 0
      },
      {
        "module": "RBBPROVISIONING-MIB",
        "object": "rbbSubModel",
        "implied": 0
      },
      {
        "module": "RBBPROVISIONING-MIB",
        "object": "rbbSubSerialNumber",
        "implied": 0
      },
      {
        "module": "RBBPROVISIONING-MIB",
        "object": "rbbSubServiceIdentifier",
        "implied": 0
      }
    ],
    "status": "current",
    "description": "This object defines the individual rows in the subscription table (rbbSubTable)"
  },
  "rbbSubVendor": {
    "name": "rbbSubVendor",
    "oid": "1.3.6.1.4.1.4839.32.1.2.1.1.1",
    "nodetype": "column",
    "class": "objecttype",
    "syntax": {
      "type": "OBJECT IDENTIFIER",
      "class": "type"
    },
    "maxaccess": "read-create",
    "status": "current",
    "description": "The Vendor part of the index that uniquely identifies this CPE"
  },
  "rbbSubModel": {
    "name": "rbbSubModel",
    "oid": "1.3.6.1.4.1.4839.32.1.2.1.1.3",
    "nodetype": "column",
    "class": "objecttype",
    "syntax": {
      "type": "RBBVendorModel",
      "class": "type"
    },
    "maxaccess": "read-create",
    "status": "current",
    "description": "The Model part of the index that uniquely identifies a CPE"
  },
  "rbbSubSerialNumber": {
    "name": "rbbSubSerialNumber",
    "oid": "1.3.6.1.4.1.4839.32.1.2.1.1.4",
    "nodetype": "column",
    "class": "objecttype",
    "syntax": {
      "type": "DisplayString",
      "class": "type"
    },
    "maxaccess": "read-create",
    "status": "current",
    "description": "The serial number part of the index that uniquely identifies a CPE"
  },
  "rbbSubServiceIdentifier": {
    "name": "rbbSubServiceIdentifier",
    "oid": "1.3.6.1.4.1.4839.32.1.2.1.1.5",
    "nodetype": "column",
    "class": "objecttype",
    "syntax": {
      "type": "RBBServiceID",
      "class": "type"
    },
    "maxaccess": "read-create",
    "status": "current",
    "description": "An Index value referring to an entry in the rbbServicesTable. This is the service-side in the customer/service subscription association."
  },
  "rbbSubVPI": {
    "name": "rbbSubVPI",
    "oid": "1.3.6.1.4.1.4839.32.1.2.1.1.6",
    "nodetype": "column",
    "class": "objecttype",
    "syntax": {
      "type": "AtmVpIdentifier",
      "class": "type"
    },
    "maxaccess": "read-create",
    "status": "current",
    "description": "The virtual path identifier to be used in the establishment of a PVC to a particular service, if the service is PVC- based."
  },
  "rbbSubVCI": {
    "name": "rbbSubVCI",
    "oid": "1.3.6.1.4.1.4839.32.1.2.1.1.7",
    "nodetype": "column",
    "class": "objecttype",
    "syntax": {
      "type": "AtmVcIdentifier",
      "class": "type"
    },
    "maxaccess": "read-create",
    "status": "current",
    "description": "The virtual circuit identifier to be used in the establishment of a PVC to a particular service, if the service is PVC-based."
  },
  "rbbSubAddr": {
    "name": "rbbSubAddr",
    "oid": "1.3.6.1.4.1.4839.32.1.2.1.1.8",
    "nodetype": "column",
    "class": "objecttype",
    "syntax": {
      "type": "AtmAddr",
      "class": "type"
    },
    "maxaccess": "read-create",
    "status": "current",
    "description": "The end-system address to be used in the establishment of an SVC to a particular service, if the service is SVC-based."
  },
  "rbbSubStatus": {
    "name": "rbbSubStatus",
    "oid": "1.3.6.1.4.1.4839.32.1.2.1.1.9",
    "nodetype": "column",
    "class": "objecttype",
    "syntax": {
      "type": "RBBServiceStatus",
      "class": "type"
    },
    "maxaccess": "read-create",
    "status": "current",
    "description": "The current status of this subscription, currently defined as up, down, or suspended."
  },
  "rbbSubRowInfo": {
    "name": "rbbSubRowInfo",
    "oid": "1.3.6.1.4.1.4839.32.1.2.1.1.10",
    "nodetype": "column",
    "class": "objecttype",
    "syntax": {
      "type": "RowStatus",
      "class": "type"
    },
    "maxaccess": "read-create",
    "status": "current"
  },
  "rbbCPETable": {
    "name": "rbbCPETable",
    "oid": "1.3.6.1.4.1.4839.32.1.3.1",
    "nodetype": "table",
    "class": "objecttype",
    "maxaccess": "not-accessible",
    "status": "current",
    "description": "This table contains a sequence of rows where each row describes a particular CPE that has identified itself to the management framework."
  },
  "rbbCPEEntry": {
    "name": "rbbCPEEntry",
    "oid": "1.3.6.1.4.1.4839.32.1.3.1.1",
    "nodetype": "row",
    "class": "objecttype",
    "maxaccess": "not-accessible",
    "indices": [
      {
        "module": "RBBPROVISIONING-MIB",
        "object": "rbbVendorOID",
        "implied": 0
      },
      {
        "module": "RBBPROVISIONING-MIB",
        "object": "rbbVendorModel",
        "implied": 0
      },
      {
        "module": "RBBPROVISIONING-MIB",
        "object": "rbbCPESerialNumber",
        "implied": 0
      }
    ],
    "status": "current",
    "description": "This object defines the individual rows in the CPE table (rbbCPETable)"
  },
  "rbbCPEAuthValue": {
    "name": "rbbCPEAuthValue",
    "oid": "1.3.6.1.4.1.4839.32.1.3.1.1.1",
    "nodetype": "column",
    "class": "objecttype",
    "syntax": {
      "type": "RBBCPEAuthType",
      "class": "type"
    },
    "maxaccess": "read-create",
    "status": "current",
    "description": "A unique identifier that uniquely identifies a particular customer or end-user"
  },
  "rbbCPEVendorOID": {
    "name": "rbbCPEVendorOID",
    "oid": "1.3.6.1.4.1.4839.32.1.3.1.1.2",
    "nodetype": "column",
    "class": "objecttype",
    "syntax": {
      "type": "OBJECT IDENTIFIER",
      "class": "type"
    },
    "maxaccess": "read-create",
    "status": "current",
    "description": "A unique object identifier that identifies a particular CPE vendor"
  },
  "rbbCPEVendorModel": {
    "name": "rbbCPEVendorModel",
    "oid": "1.3.6.1.4.1.4839.32.1.3.1.1.3",
    "nodetype": "column",
    "class": "objecttype",
    "syntax": {
      "type": "RBBVendorModel",
      "class": "type"
    },
    "maxaccess": "read-create",
    "status": "current"
  },
  "rbbCPEStatus": {
    "name": "rbbCPEStatus",
    "oid": "1.3.6.1.4.1.4839.32.1.3.1.1.4",
    "nodetype": "column",
    "class": "objecttype",
    "syntax": {
      "type": "INTEGER",
      "class": "type"
    },
    "maxaccess": "read-create",
    "status": "current",
    "description": "An integer enumeration that identifies the current status of the CPE device"
  },
  "rbbCPESubCount": {
    "name": "rbbCPESubCount",
    "oid": "1.3.6.1.4.1.4839.32.1.3.1.1.5",
    "nodetype": "column",
    "class": "objecttype",
    "syntax": {
      "type": "INTEGER",
      "class": "type"
    },
    "maxaccess": "read-create",
    "status": "current",
    "description": "An integer value representing the number of service subscriptions that exist in the subscription table for this customer"
  },
  "rbbCPESubAggrSpeed": {
    "name": "rbbCPESubAggrSpeed",
    "oid": "1.3.6.1.4.1.4839.32.1.3.1.1.6",
    "nodetype": "column",
    "class": "objecttype",
    "syntax": {
      "type": "INTEGER",
      "class": "type"
    },
    "maxaccess": "read-create",
    "status": "current",
    "description": "The total aggregate bandwidth required by all active subscriptions for this CPE customer."
  },
  "rbbCPECustContact": {
    "name": "rbbCPECustContact",
    "oid": "1.3.6.1.4.1.4839.32.1.3.1.1.7",
    "nodetype": "column",
    "class": "objecttype",
    "syntax": {
      "type": "RBBMailAddr",
      "class": "type"
    },
    "maxaccess": "read-create",
    "status": "current",
    "description": "The email address for the individual at the customer premises that is responsible for the broadband service."
  },
  "rbbCPESerialNumber": {
    "name": "rbbCPESerialNumber",
    "oid": "1.3.6.1.4.1.4839.32.1.3.1.1.8",
    "nodetype": "column",
    "class": "objecttype",
    "syntax": {
      "type": "RBBCPESerialNumber",
      "class": "type"
    },
    "maxaccess": "read-create",
    "status": "current",
    "description": "The unique hardware address or serial number associated with the CPE"
  },
  "rbbCPETrapEnable": {
    "name": "rbbCPETrapEnable",
    "oid": "1.3.6.1.4.1.4839.32.1.3.1.1.9",
    "nodetype": "column",
    "class": "objecttype",
    "syntax": {
      "type": "INTEGER",
      "class": "type"
    },
    "maxaccess": "read-create",
    "status": "current",
    "description": "A boolean value representing whether or not service-related traps are enabled or disabled for this CPE device."
  },
  "rbbCPECurrentImage": {
    "name": "rbbCPECurrentImage",
    "oid": "1.3.6.1.4.1.4839.32.1.3.1.1.10",
    "nodetype": "column",
    "class": "objecttype",
    "syntax": {
      "type": "RBBURLType",
      "class": "type"
    },
    "maxaccess": "read-create",
    "status": "current",
    "description": "A URL string pointing to the current image that is installed in this particular CPE/customer site"
  },
  "rbbCPEIpAddress": {
    "name": "rbbCPEIpAddress",
    "oid": "1.3.6.1.4.1.4839.32.1.3.1.1.11",
    "nodetype": "column",
    "class": "objecttype",
    "syntax": {
      "type": "IpAddress",
      "class": "type"
    },
    "maxaccess": "read-create",
    "status": "current"
  },
  "rbbCPERowInfo": {
    "name": "rbbCPERowInfo",
    "oid": "1.3.6.1.4.1.4839.32.1.3.1.1.12",
    "nodetype": "column",
    "class": "objecttype",
    "syntax": {
      "type": "RowStatus",
      "class": "type"
    },
    "maxaccess": "read-create",
    "status": "current"
  },
  "rbbVendorTable": {
    "name": "rbbVendorTable",
    "oid": "1.3.6.1.4.1.4839.32.1.4.1",
    "nodetype": "table",
    "class": "objecttype",
    "maxaccess": "not-accessible",
    "status": "current",
    "description": "Vendor table describing types of CPE supported, and associated CPE management details."
  },
  "rbbVendorEntry": {
    "name": "rbbVendorEntry",
    "oid": "1.3.6.1.4.1.4839.32.1.4.1.1",
    "nodetype": "row",
    "class": "objecttype",
    "maxaccess": "not-accessible",
    "indices": [
      {
        "module": "RBBPROVISIONING-MIB",
        "object": "rbbVendorOID",
        "implied": 0
      },
      {
        "module": "RBBPROVISIONING-MIB",
        "object": "rbbVendorModel",
        "implied": 0
      }
    ],
    "status": "current",
    "description": "Each row describes a particular vendor model of CPE"
  },
  "rbbVendorOID": {
    "name": "rbbVendorOID",
    "oid": "1.3.6.1.4.1.4839.32.1.4.1.1.1",
    "nodetype": "column",
    "class": "objecttype",
    "syntax": {
      "type": "OBJECT IDENTIFIER",
      "class": "type"
    },
    "maxaccess": "read-create",
    "status": "current",
    "description": "A unique object identifier value associated with a particular vendor of CPE"
  },
  "rbbVendorModel": {
    "name": "rbbVendorModel",
    "oid": "1.3.6.1.4.1.4839.32.1.4.1.1.2",
    "nodetype": "column",
    "class": "objecttype",
    "syntax": {
      "type": "RBBVendorModel",
      "class": "type"
    },
    "maxaccess": "read-create",
    "status": "current",
    "description": "A human-readable string representing the model number for a particular vendor's CPE device"
  },
  "rbbVendorImageURL": {
    "name": "rbbVendorImageURL",
    "oid": "1.3.6.1.4.1.4839.32.1.4.1.1.3",
    "nodetype": "column",
    "class": "objecttype",
    "syntax": {
      "type": "RBBURLType",
      "class": "type"
    },
    "maxaccess": "read-create",
    "status": "current",
    "description": "A URL string representing the most current version of firmware available for this CPE model"
  },
  "rbbVendorRowInfo": {
    "name": "rbbVendorRowInfo",
    "oid": "1.3.6.1.4.1.4839.32.1.4.1.1.4",
    "nodetype": "column",
    "class": "objecttype",
    "syntax": {
      "type": "RowStatus",
      "class": "type"
    },
    "maxaccess": "read-create",
    "status": "current"
  },
  "rbbSrvGrpSerialNumber": {
    "name": "rbbSrvGrpSerialNumber",
    "oid": "1.3.6.1.4.1.4839.32.1.5",
    "nodetype": "scalar",
    "class": "objecttype",
    "syntax": {
      "type": "Counter32",
      "class": "type"
    },
    "maxaccess": "read-only",
    "status": "current"
  },
  "rbbSubGrpSerialNumber": {
    "name": "rbbSubGrpSerialNumber",
    "oid": "1.3.6.1.4.1.4839.32.1.6",
    "nodetype": "scalar",
    "class": "objecttype",
    "syntax": {
      "type": "Counter32",
      "class": "type"
    },
    "maxaccess": "read-only",
    "status": "current"
  },
  "rbbCPEGrpSerialNumber": {
    "name": "rbbCPEGrpSerialNumber",
    "oid": "1.3.6.1.4.1.4839.32.1.7",
    "nodetype": "scalar",
    "class": "objecttype",
    "syntax": {
      "type": "Counter32",
      "class": "type"
    },
    "maxaccess": "read-only",
    "status": "current"
  },
  "rbbVendorGrpSerialNumber": {
    "name": "rbbVendorGrpSerialNumber",
    "oid": "1.3.6.1.4.1.4839.32.1.8",
    "nodetype": "scalar",
    "class": "objecttype",
    "syntax": {
      "type": "Counter32",
      "class": "type"
    },
    "maxaccess": "read-only",
    "status": "current"
  },
  "rbbSubNotify": {
    "name": "rbbSubNotify",
    "oid": "1.3.6.1.4.1.4839.32.1.12.1",
    "class": "notificationtype",
    "objects": [
      {
        "module": "RBBPROVISIONING-MIB",
        "object": "rbbSubVendor"
      },
      {
        "module": "RBBPROVISIONING-MIB",
        "object": "rbbSubModel"
      },
      {
        "module": "RBBPROVISIONING-MIB",
        "object": "rbbSubSerialNumber"
      },
      {
        "module": "RBBPROVISIONING-MIB",
        "object": "rbbSubServiceIdentifier"
      }
    ],
    "status": "current",
    "description": "This notification indicates that a new subscription has been added to, or when a subscription has been deleted from the rbbSubTable in the rbbSubGroup. The notification includes which specific index was added so that the manager does not have to implement a search for changes."
  },
  "rbbPowerUpNotify": {
    "name": "rbbPowerUpNotify",
    "oid": "1.3.6.1.4.1.4839.32.1.12.2",
    "class": "notificationtype",
    "objects": [
      {
        "module": "RBBPROVISIONING-MIB",
        "object": "rbbCPEVendorOID"
      },
      {
        "module": "RBBPROVISIONING-MIB",
        "object": "rbbCPEVendorModel"
      },
      {
        "module": "RBBPROVISIONING-MIB",
        "object": "rbbCPESerialNumber"
      }
    ],
    "status": "current"
  },
  "meta": {
    "comments": [
      "ASN.1 source file:///Users/neermitt/kusanagi/mibs.snmplabs.com/asn1/RBBPROVISIONING-MIB",
      "Produced by pysmi-0.3.4 at Fri May 24 21:14:00 2019",
      "On host NEERMITT-M-J0NV platform Darwin version 18.6.0 by user neermitt",
      "Using Python version 3.7.3 (default, Mar 27 2019, 09:23:15) "
    ],
    "module": "RBBPROVISIONING-MIB"
  }
}