{
  "imports": {
    "class": "imports",
    "SNMPv2-CONF": [
      "MODULE-COMPLIANCE",
      "OBJECT-GROUP",
      "NOTIFICATION-GROUP"
    ],
    "SNMPv2-SMI": [
      "TimeTicks",
      "IpAddress",
      "iso",
      "Bits",
      "Counter32",
      "Counter64",
      "Unsigned32",
      "MODULE-IDENTITY",
      "OBJECT-TYPE",
      "enterprises",
      "OBJECT-IDENTITY",
      "NOTIFICATION-TYPE",
      "Integer32",
      "Gauge32",
      "MibIdentifier"
    ],
    "SNMPv2-TC": [
      "MacAddress",
      "DisplayString",
      "TEXTUAL-CONVENTION"
    ]
  },
  "schleifenbauer": {
    "name": "schleifenbauer",
    "oid": "1.3.6.1.4.1.31034",
    "class": "moduleidentity",
    "lastupdated": "201504131700Z",
    "organization": "Schleifenbauer Engineering",
    "contactinfo": "Schleifenbauer Engineering Alain Schuermans Chief Technology Officer Turnhoutseweg 22 5541 NX Reusel The Netherlands t. +31 73 5230256 f. +31 73 5212383 alain@schleifenbauer.eu www.schleifenbauer.eu",
    "description": "This MIB describes the functions of the Schleifenbauer device family."
  },
  "DeciAmps": {
    "name": "DeciAmps",
    "class": "textualconvention",
    "type": {
      "type": "Integer32",
      "class": "type"
    },
    "displayhint": "d-2",
    "status": "current",
    "description": "Data type for reporting measurements and thresholds associated with current sensors. If the underlying hardware sensor indicates 1.1 amp, then the SNMP agent will report a value of 11 DeciAmps. The value is scaled in this manner as a way to deal with floating point types that SNMP does not currently support."
  },
  "DeciCelsius": {
    "name": "DeciCelsius",
    "class": "textualconvention",
    "type": {
      "type": "Integer32",
      "class": "type"
    },
    "displayhint": "d-2",
    "status": "current",
    "description": "Data type for reporting sensor readings associated with temperature sensors. If the underlying hardware sensor indicates 20.1 degree Celsius, then the SNMP agent will report a value of 201 tenth degrees Celsius. The value is scaled in this manner as a way to deal with floating point types that SNMP does not currently support."
  },
  "DeciPowerFactor": {
    "name": "DeciPowerFactor",
    "class": "textualconvention",
    "type": {
      "type": "Integer32",
      "class": "type"
    },
    "displayhint": "d-2",
    "status": "current",
    "description": "Data type for reporting measurements associated with power factor calculation. The power factor of an AC power system is defined as the ratio of the real or active power to the apparent power and is a number between 0 and 1. A DeciPowerFactor value is calculated by taking this ratio and multiplying by 1000. A power factor of 98.3% will be reported as 983. The power factor is used to indicate how efficiently a particular load is utilizing energy."
  },
  "DeciValue": {
    "name": "DeciValue",
    "class": "textualconvention",
    "type": {
      "type": "Integer32",
      "class": "type"
    },
    "displayhint": "d-2",
    "status": "current",
    "description": "Data type for reporting generic measurements associated with environmental sensors. If the underlying hardware sensor indicates 21.1 degree, then the SNMP agent will report a value of 211 DeciValue. The value is scaled in this manner as a way to deal with floating point types that SNMP does not currently support."
  },
  "DeciVolts": {
    "name": "DeciVolts",
    "class": "textualconvention",
    "type": {
      "type": "Integer32",
      "class": "type"
    },
    "displayhint": "d-2",
    "status": "current",
    "description": "Data type for reporting measurements and thresholds associated with voltage sensors. If the underlying hardware sensor indicates 231.1 volts, then the SNMP agent will report a value of 2311 DeciVolts. The value is scaled in this manner as a way to deal with floating point types that SNMP does not currently support."
  },
  "KiloWattHour": {
    "name": "KiloWattHour",
    "class": "textualconvention",
    "type": {
      "type": "Integer32",
      "class": "type"
    },
    "displayhint": "d",
    "status": "current",
    "description": "Data type for reporting measurements associated with energy accumulation sensors. If the underlying hardware sensor indicates 1 kWh, then the SNMP agent will report a value of 1 kWh. No scaling is performed for this type."
  },
  "MilliSeconds": {
    "name": "MilliSeconds",
    "class": "textualconvention",
    "type": {
      "type": "Integer32",
      "class": "type"
    },
    "displayhint": "d",
    "status": "current",
    "description": "The unit of duration for some settings"
  },
  "Seconds": {
    "name": "Seconds",
    "class": "textualconvention",
    "type": {
      "type": "Integer32",
      "class": "type"
    },
    "displayhint": "d",
    "status": "current",
    "description": "The unit of duration for some settings"
  },
  "device0": {
    "name": "device0",
    "oid": "1.3.6.1.4.1.31034.2",
    "class": "objectidentity"
  },
  "identification": {
    "name": "identification",
    "oid": "1.3.6.1.4.1.31034.2.3",
    "class": "objectidentity"
  },
  "spdmVersion": {
    "name": "spdmVersion",
    "oid": "1.3.6.1.4.1.31034.2.3.1",
    "nodetype": "column",
    "class": "objecttype",
    "syntax": {
      "type": "Integer32",
      "class": "type",
      "constraints": {
        "range": [
          {
            "min": 0,
            "max": 9999
          }
        ]
      }
    },
    "maxaccess": "read-only",
    "status": "current",
    "description": "Data model version, currently 1.10"
  },
  "firmwareVersion": {
    "name": "firmwareVersion",
    "oid": "1.3.6.1.4.1.31034.2.3.2",
    "nodetype": "column",
    "class": "objecttype",
    "syntax": {
      "type": "Integer32",
      "class": "type",
      "constraints": {
        "range": [
          {
            "min": 0,
            "max": 9999
          }
        ]
      }
    },
    "maxaccess": "read-only",
    "status": "current",
    "description": "The units firmware revision number."
  },
  "buildNumber": {
    "name": "buildNumber",
    "oid": "1.3.6.1.4.1.31034.2.3.3",
    "nodetype": "scalar",
    "class": "objecttype",
    "syntax": {
      "type": "DisplayString",
      "class": "type"
    },
    "maxaccess": "read-only",
    "status": "current",
    "description": "Date and time of latest build of the firmware."
  },
  "salesOrderNumber": {
    "name": "salesOrderNumber",
    "oid": "1.3.6.1.4.1.31034.2.3.4",
    "nodetype": "column",
    "class": "objecttype",
    "syntax": {
      "type": "DisplayString",
      "class": "type"
    },
    "maxaccess": "read-only",
    "status": "current",
    "description": "SP sales order number."
  },
  "productId": {
    "name": "productId",
    "oid": "1.3.6.1.4.1.31034.2.3.5",
    "nodetype": "column",
    "class": "objecttype",
    "syntax": {
      "type": "DisplayString",
      "class": "type"
    },
    "maxaccess": "read-only",
    "status": "current",
    "description": "SP product id."
  },
  "serialNumber": {
    "name": "serialNumber",
    "oid": "1.3.6.1.4.1.31034.2.3.6",
    "nodetype": "column",
    "class": "objecttype",
    "syntax": {
      "type": "DisplayString",
      "class": "type"
    },
    "maxaccess": "read-only",
    "status": "current",
    "description": "SP serial number."
  },
  "hardwareAddress": {
    "name": "hardwareAddress",
    "oid": "1.3.6.1.4.1.31034.2.3.7",
    "nodetype": "column",
    "class": "objecttype",
    "syntax": {
      "type": "DisplayString",
      "class": "type"
    },
    "maxaccess": "read-only",
    "status": "current",
    "description": "Hardware serial number; cannot be changed. Can be used as backup unit address. format as 3 unsigned ints separated by dashes: int - int - int"
  },
  "macAddress": {
    "name": "macAddress",
    "oid": "1.3.6.1.4.1.31034.2.3.8",
    "nodetype": "scalar",
    "class": "objecttype",
    "syntax": {
      "type": "DisplayString",
      "class": "type"
    },
    "maxaccess": "read-only",
    "status": "current",
    "description": "The ethernet interfaces unique hardware address."
  },
  "unitAddress": {
    "name": "unitAddress",
    "oid": "1.3.6.1.4.1.31034.2.3.9",
    "nodetype": "column",
    "class": "objecttype",
    "syntax": {
      "type": "Integer32",
      "class": "type",
      "constraints": {
        "range": [
          {
            "min": 0,
            "max": 65535
          }
        ]
      }
    },
    "maxaccess": "read-write",
    "status": "current",
    "description": "User defined address; this will be used for addressing the unit."
  },
  "deviceName": {
    "name": "deviceName",
    "oid": "1.3.6.1.4.1.31034.2.3.10",
    "nodetype": "scalar",
    "class": "objecttype",
    "syntax": {
      "type": "DisplayString",
      "class": "type"
    },
    "maxaccess": "read-write",
    "status": "current",
    "description": "User configurable device name or identifier."
  },
  "deviceLocation": {
    "name": "deviceLocation",
    "oid": "1.3.6.1.4.1.31034.2.3.11",
    "nodetype": "scalar",
    "class": "objecttype",
    "syntax": {
      "type": "DisplayString",
      "class": "type"
    },
    "maxaccess": "read-write",
    "status": "current",
    "description": "User configurable device location identifier."
  },
  "vanityTag": {
    "name": "vanityTag",
    "oid": "1.3.6.1.4.1.31034.2.3.12",
    "nodetype": "scalar",
    "class": "objecttype",
    "syntax": {
      "type": "DisplayString",
      "class": "type"
    },
    "maxaccess": "read-write",
    "status": "current",
    "description": "Characters to be displayed as vanity tekst in display."
  },
  "configuration": {
    "name": "configuration",
    "oid": "1.3.6.1.4.1.31034.2.4",
    "class": "objectidentity"
  },
  "noPhases": {
    "name": "noPhases",
    "oid": "1.3.6.1.4.1.31034.2.4.1",
    "nodetype": "column",
    "class": "objecttype",
    "syntax": {
      "type": "Integer32",
      "class": "type",
      "constraints": {
        "range": [
          {
            "min": 0,
            "max": 3
          }
        ]
      }
    },
    "maxaccess": "read-only",
    "status": "current",
    "description": "Either zero, one or three for no input metering, single or three phase system"
  },
  "noOutletsTotal": {
    "name": "noOutletsTotal",
    "oid": "1.3.6.1.4.1.31034.2.4.2",
    "nodetype": "column",
    "class": "objecttype",
    "syntax": {
      "type": "Integer32",
      "class": "type",
      "constraints": {
        "range": [
          {
            "min": 0,
            "max": 99
          }
        ]
      }
    },
    "maxaccess": "read-only",
    "status": "current",
    "description": "Total number of outlets, even hardwired without switch/measure modules."
  },
  "noSwitchedOutlets": {
    "name": "noSwitchedOutlets",
    "oid": "1.3.6.1.4.1.31034.2.4.3",
    "nodetype": "column",
    "class": "objecttype",
    "syntax": {
      "type": "Integer32",
      "class": "type",
      "constraints": {
        "range": [
          {
            "min": 0,
            "max": 48
          }
        ]
      }
    },
    "maxaccess": "read-only",
    "status": "current",
    "description": "Number of switched outlets. If outlet numbering is non-contiguous: the highest outlet number."
  },
  "noMeasuredOutlets": {
    "name": "noMeasuredOutlets",
    "oid": "1.3.6.1.4.1.31034.2.4.4",
    "nodetype": "column",
    "class": "objecttype",
    "syntax": {
      "type": "Integer32",
      "class": "type",
      "constraints": {
        "range": [
          {
            "min": 0,
            "max": 48
          }
        ]
      }
    },
    "maxaccess": "read-only",
    "status": "current",
    "description": "Number of measured outlets. If outlet numbering is non-contiguous: the highest outlet number."
  },
  "noSensors": {
    "name": "noSensors",
    "oid": "1.3.6.1.4.1.31034.2.4.5",
    "nodetype": "scalar",
    "class": "objecttype",
    "syntax": {
      "type": "Integer32",
      "class": "type",
      "constraints": {
        "range": [
          {
            "min": 0,
            "max": 4
          }
        ]
      }
    },
    "maxaccess": "read-only",
    "status": "current",
    "description": "The number of external, digital environmental sensors: 0 for none, 1 to 16 depending on number of reported sensors"
  },
  "maximumLoad": {
    "name": "maximumLoad",
    "oid": "1.3.6.1.4.1.31034.2.4.6",
    "nodetype": "column",
    "class": "objecttype",
    "syntax": {
      "type": "Integer32",
      "class": "type",
      "constraints": {
        "range": [
          {
            "min": 0,
            "max": 32
          }
        ]
      }
    },
    "maxaccess": "read-only",
    "status": "current",
    "description": "Maximum rated load of device per phase, usually either 16 or 32 A."
  },
  "systemstatus": {
    "name": "systemstatus",
    "oid": "1.3.6.1.4.1.31034.2.5",
    "class": "objectidentity"
  },
  "deviceStatusCode": {
    "name": "deviceStatusCode",
    "oid": "1.3.6.1.4.1.31034.2.5.1",
    "nodetype": "column",
    "class": "objecttype",
    "syntax": {
      "type": "Integer32",
      "class": "type",
      "constraints": {
        "range": [
          {
            "min": 0,
            "max": 255
          }
        ]
      }
    },
    "maxaccess": "read-only",
    "status": "current",
    "description": "Returns an internal status or error code. 0 = OK, 16 = watchdog timer caused reset, 128 = slave module was reset, 144 = both previous."
  },
  "temperatureAlert": {
    "name": "temperatureAlert",
    "oid": "1.3.6.1.4.1.31034.2.5.2",
    "nodetype": "column",
    "class": "objecttype",
    "syntax": {
      "type": "Integer32",
      "class": "type",
      "constraints": {
        "range": [
          {
            "min": 0,
            "max": 2
          }
        ]
      }
    },
    "maxaccess": "read-only",
    "status": "current",
    "description": "An alert has been raised due to temperature exceeding treshhold; 0= no alert; 1= internal unit temp, 2= external sensor."
  },
  "inputCurrentAlert": {
    "name": "inputCurrentAlert",
    "oid": "1.3.6.1.4.1.31034.2.5.3",
    "nodetype": "column",
    "class": "objecttype",
    "syntax": {
      "type": "Integer32",
      "class": "type",
      "constraints": {
        "range": [
          {
            "min": 0,
            "max": 3
          }
        ]
      }
    },
    "maxaccess": "read-only",
    "status": "current",
    "description": "An alert has been raised due to current exceeding treshhold; 0=no alert; 1-3 for input phase."
  },
  "outputCurrentAlert": {
    "name": "outputCurrentAlert",
    "oid": "1.3.6.1.4.1.31034.2.5.4",
    "nodetype": "column",
    "class": "objecttype",
    "syntax": {
      "type": "Integer32",
      "class": "type",
      "constraints": {
        "range": [
          {
            "min": 0,
            "max": 48
          }
        ]
      }
    },
    "maxaccess": "read-only",
    "status": "current",
    "description": "An alert has been raised due to current exceeding treshhold; 0=no alert; 1-48 for outlet."
  },
  "inputVoltageAlert": {
    "name": "inputVoltageAlert",
    "oid": "1.3.6.1.4.1.31034.2.5.5",
    "nodetype": "column",
    "class": "objecttype",
    "syntax": {
      "type": "Integer32",
      "class": "type",
      "constraints": {
        "range": [
          {
            "min": 0,
            "max": 3
          }
        ]
      }
    },
    "maxaccess": "read-only",
    "status": "current",
    "description": "An alert has been raised due to a voltage dip; 0=no alert; 1-3 for input phase."
  },
  "oCurrentDropAlert": {
    "name": "oCurrentDropAlert",
    "oid": "1.3.6.1.4.1.31034.2.5.6",
    "nodetype": "column",
    "class": "objecttype",
    "syntax": {
      "type": "Integer32",
      "class": "type",
      "constraints": {
        "range": [
          {
            "min": 0,
            "max": 103
          }
        ]
      }
    },
    "maxaccess": "read-only",
    "status": "current",
    "description": "An alert has been raised due to the current of a measured outlet suddenly dropping to near zero, possibly indicating a blown fuse; 0=no alert; 1-48 for outlet."
  },
  "iCurrentDropAlert": {
    "name": "iCurrentDropAlert",
    "oid": "1.3.6.1.4.1.31034.2.5.7",
    "nodetype": "column",
    "class": "objecttype",
    "syntax": {
      "type": "Integer32",
      "class": "type",
      "constraints": {
        "range": [
          {
            "min": 0,
            "max": 3
          }
        ]
      }
    },
    "maxaccess": "read-only",
    "status": "current",
    "description": "An alert has been raised due to the current of a measured input suddenly dropping to near zero, possibly indicating a blown fuse; 0=no alert; 1-3 for phase."
  },
  "reset": {
    "name": "reset",
    "oid": "1.3.6.1.4.1.31034.2.6",
    "class": "objectidentity"
  },
  "rebootDevice": {
    "name": "rebootDevice",
    "oid": "1.3.6.1.4.1.31034.2.6.1",
    "nodetype": "scalar",
    "class": "objecttype",
    "syntax": {
      "type": "Integer32",
      "class": "type"
    },
    "maxaccess": "read-write",
    "status": "current",
    "description": "Warm reboot/reset of device; note: this will have no effect on outlet status!"
  },
  "resetAlerts": {
    "name": "resetAlerts",
    "oid": "1.3.6.1.4.1.31034.2.6.2",
    "nodetype": "scalar",
    "class": "objecttype",
    "syntax": {
      "type": "Integer32",
      "class": "type"
    },
    "maxaccess": "read-write",
    "status": "current",
    "description": "Reset all alert signals."
  },
  "zeroInputKWhSubtotal": {
    "name": "zeroInputKWhSubtotal",
    "oid": "1.3.6.1.4.1.31034.2.6.3",
    "nodetype": "scalar",
    "class": "objecttype",
    "syntax": {
      "type": "Integer32",
      "class": "type"
    },
    "maxaccess": "read-write",
    "status": "current",
    "description": "Reset of input kWh subtotal counters to zero."
  },
  "zeroOutKWhSubtotal": {
    "name": "zeroOutKWhSubtotal",
    "oid": "1.3.6.1.4.1.31034.2.6.4",
    "nodetype": "scalar",
    "class": "objecttype",
    "syntax": {
      "type": "Integer32",
      "class": "type"
    },
    "maxaccess": "read-write",
    "status": "current",
    "description": "Reset of outlet kWh subtotal counter to zero."
  },
  "resetPeakValues": {
    "name": "resetPeakValues",
    "oid": "1.3.6.1.4.1.31034.2.6.5",
    "nodetype": "scalar",
    "class": "objecttype",
    "syntax": {
      "type": "Integer32",
      "class": "type"
    },
    "maxaccess": "read-write",
    "status": "current",
    "description": "Reset all peak values to zero, as well input as output metering, voltages dips, current peaks and temperatures."
  },
  "settings": {
    "name": "settings",
    "oid": "1.3.6.1.4.1.31034.2.7",
    "class": "objectidentity"
  },
  "general": {
    "name": "general",
    "oid": "1.3.6.1.4.1.31034.2.7.1",
    "class": "objectidentity"
  },
  "peakDuration": {
    "name": "peakDuration",
    "oid": "1.3.6.1.4.1.31034.2.7.1.4",
    "nodetype": "scalar",
    "class": "objecttype",
    "syntax": {
      "type": "MilliSeconds",
      "class": "type"
    },
    "maxaccess": "read-write",
    "status": "current",
    "description": "A current peak should last at least [stpkdr] MilliSeconds before an alert is raised; max about a minute."
  },
  "fixedOutletDelay": {
    "name": "fixedOutletDelay",
    "oid": "1.3.6.1.4.1.31034.2.7.1.5",
    "nodetype": "scalar",
    "class": "objecttype",
    "syntax": {
      "type": "MilliSeconds",
      "class": "type"
    },
    "maxaccess": "read-write",
    "status": "current",
    "description": "Minimal delay between two successive relay switches in milliseconds. Minimal delay is 100 ms. Will always be respected!"
  },
  "powerSaverMode": {
    "name": "powerSaverMode",
    "oid": "1.3.6.1.4.1.31034.2.7.1.6",
    "nodetype": "scalar",
    "class": "objecttype",
    "syntax": {
      "type": "Seconds",
      "class": "type"
    },
    "maxaccess": "read-write",
    "status": "current",
    "description": "Set backlight on time in seconds; 0 keeps display always on. Note that keeping the backlight on may decrease luminosity over time. Setting this to other values than 10, 60, 120 or 240 is incompatible with the gateway!"
  },
  "outletPowerupMode": {
    "name": "outletPowerupMode",
    "oid": "1.3.6.1.4.1.31034.2.7.1.7",
    "nodetype": "scalar",
    "class": "objecttype",
    "syntax": {
      "type": "Integer32",
      "class": "type",
      "constraints": {
        "range": [
          {
            "min": 0,
            "max": 2
          }
        ]
      }
    },
    "maxaccess": "read-write",
    "status": "current",
    "description": "Behaviour of outlet on power-up: 0=off; 1=same state as at power down; 2=same state, but delayed by individual delay timer."
  },
  "maximumTemperature": {
    "name": "maximumTemperature",
    "oid": "1.3.6.1.4.1.31034.2.7.1.8",
    "nodetype": "scalar",
    "class": "objecttype",
    "syntax": {
      "type": "Integer32",
      "class": "type",
      "constraints": {
        "range": [
          {
            "min": 0,
            "max": 99
          }
        ]
      }
    },
    "maxaccess": "read-write",
    "status": "current",
    "description": "An alert should be generated whenever the temperature of the first connected T sensor is above this value. Zero means disabled."
  },
  "displayOrientation": {
    "name": "displayOrientation",
    "oid": "1.3.6.1.4.1.31034.2.7.1.9",
    "nodetype": "scalar",
    "class": "objecttype",
    "syntax": {
      "type": "Integer32",
      "class": "type",
      "constraints": {
        "range": [
          {
            "min": 0,
            "max": 4
          }
        ]
      }
    },
    "maxaccess": "read-write",
    "status": "current",
    "description": "0 no display; display off; 1 vertical, display on top; 2 vertical, upside down; 3 horizontal, display at left; 4 horizontal, display at right"
  },
  "localAlertReset": {
    "name": "localAlertReset",
    "oid": "1.3.6.1.4.1.31034.2.7.1.10",
    "nodetype": "scalar",
    "class": "objecttype",
    "syntax": {
      "type": "Integer32",
      "class": "type"
    },
    "maxaccess": "read-write",
    "status": "current",
    "description": "Allow alerts to be reset locally on device by pushing one of the buttons. [replaces dipDuration]"
  },
  "currentDropDetection": {
    "name": "currentDropDetection",
    "oid": "1.3.6.1.4.1.31034.2.7.1.11",
    "nodetype": "scalar",
    "class": "objecttype",
    "syntax": {
      "type": "Integer32",
      "class": "type",
      "constraints": {
        "range": [
          {
            "min": 0,
            "max": 3
          }
        ]
      }
    },
    "maxaccess": "read-write",
    "status": "current",
    "description": "Enables the current drop detection function. 0 = always off (default), 1 = input (s) only, 2 = output(s) only, 3 = both inputs and outputs."
  },
  "wirelessDisplayPower": {
    "name": "wirelessDisplayPower",
    "oid": "1.3.6.1.4.1.31034.2.7.1.12",
    "nodetype": "scalar",
    "class": "objecttype",
    "syntax": {
      "type": "Integer32",
      "class": "type"
    },
    "maxaccess": "read-write",
    "status": "current",
    "description": "Controls the transit power of the wireless display transciever (if installed). Set to zero to completely disable the module."
  },
  "inputmeasuresTable": {
    "name": "inputmeasuresTable",
    "oid": "1.3.6.1.4.1.31034.2.8",
    "nodetype": "table",
    "class": "objecttype",
    "maxaccess": "not-accessible",
    "status": "current",
    "description": "This table contains all measures related to the measured inputs of the DEVICE. Note: either 1 or 3 channels, depending on number of phases measured."
  },
  "inputmeasuresEntry": {
    "name": "inputmeasuresEntry",
    "oid": "1.3.6.1.4.1.31034.2.8.1",
    "nodetype": "row",
    "class": "objecttype",
    "maxaccess": "not-accessible",
    "indices": [
      {
        "module": "SDEVICE-MIB",
        "object": "channelIndex6",
        "implied": 0
      }
    ],
    "status": "current",
    "description": "The record containing the registers for the channel selected by channelIndex."
  },
  "channelIndex6": {
    "name": "channelIndex6",
    "oid": "1.3.6.1.4.1.31034.2.8.1.1",
    "nodetype": "column",
    "class": "objecttype",
    "syntax": {
      "type": "Integer32",
      "class": "type",
      "constraints": {
        "range": [
          {
            "min": 1,
            "max": 48
          }
        ]
      }
    },
    "maxaccess": "not-accessible",
    "status": "current",
    "description": "The channel. Its value ranges between 1 and 48, depending on the number of channels, usually 1."
  },
  "kWhTotalI": {
    "name": "kWhTotalI",
    "oid": "1.3.6.1.4.1.31034.2.8.1.2",
    "nodetype": "column",
    "class": "objecttype",
    "syntax": {
      "type": "KiloWattHour",
      "class": "type"
    },
    "maxaccess": "read-only",
    "status": "current",
    "description": "Either the only phase in a single phase measurement; or one of the three phases in a multiphase measurement."
  },
  "kWhSubtotalI": {
    "name": "kWhSubtotalI",
    "oid": "1.3.6.1.4.1.31034.2.8.1.3",
    "nodetype": "column",
    "class": "objecttype",
    "syntax": {
      "type": "KiloWattHour",
      "class": "type"
    },
    "maxaccess": "read-only",
    "status": "current",
    "description": "kWh subtotal register of the only phase in a single phase measurement; or one of three phases in a multiphase measurement. Reset to zero with [rsimks]."
  },
  "powerFactorI": {
    "name": "powerFactorI",
    "oid": "1.3.6.1.4.1.31034.2.8.1.4",
    "nodetype": "column",
    "class": "objecttype",
    "syntax": {
      "type": "DeciPowerFactor",
      "class": "type"
    },
    "maxaccess": "read-only",
    "status": "current",
    "description": "The effective power factor in percent."
  },
  "actualCurrentI": {
    "name": "actualCurrentI",
    "oid": "1.3.6.1.4.1.31034.2.8.1.5",
    "nodetype": "column",
    "class": "objecttype",
    "syntax": {
      "type": "DeciAmps",
      "class": "type"
    },
    "maxaccess": "read-only",
    "status": "current",
    "description": "Actual apparent, RMS current."
  },
  "peakCurrentI": {
    "name": "peakCurrentI",
    "oid": "1.3.6.1.4.1.31034.2.8.1.6",
    "nodetype": "column",
    "class": "objecttype",
    "syntax": {
      "type": "DeciAmps",
      "class": "type"
    },
    "maxaccess": "read-only",
    "status": "current",
    "description": "Peak apparent, RMS current; highest value since last reset of the alerts."
  },
  "actualVoltageI": {
    "name": "actualVoltageI",
    "oid": "1.3.6.1.4.1.31034.2.8.1.7",
    "nodetype": "column",
    "class": "objecttype",
    "syntax": {
      "type": "DeciVolts",
      "class": "type"
    },
    "maxaccess": "read-only",
    "status": "current",
    "description": "The actual voltage."
  },
  "minVoltageI": {
    "name": "minVoltageI",
    "oid": "1.3.6.1.4.1.31034.2.8.1.8",
    "nodetype": "column",
    "class": "objecttype",
    "syntax": {
      "type": "DeciVolts",
      "class": "type"
    },
    "maxaccess": "read-only",
    "status": "current",
    "description": "RMS voltage dip; lowest value since reset of alerts."
  },
  "powerVAI": {
    "name": "powerVAI",
    "oid": "1.3.6.1.4.1.31034.2.8.1.9",
    "nodetype": "column",
    "class": "objecttype",
    "syntax": {
      "type": "Integer32",
      "class": "type"
    },
    "maxaccess": "read-only",
    "status": "current",
    "description": "Power value calculated, not in data model of device."
  },
  "powerWattI": {
    "name": "powerWattI",
    "oid": "1.3.6.1.4.1.31034.2.8.1.10",
    "nodetype": "column",
    "class": "objecttype",
    "syntax": {
      "type": "Integer32",
      "class": "type"
    },
    "maxaccess": "read-only",
    "status": "current",
    "description": "Power value calculated by the gateway, not in data model of device."
  },
  "maxInletAmps": {
    "name": "maxInletAmps",
    "oid": "1.3.6.1.4.1.31034.2.8.1.11",
    "nodetype": "column",
    "class": "objecttype",
    "syntax": {
      "type": "DeciAmps",
      "class": "type"
    },
    "maxaccess": "read-write",
    "status": "current",
    "description": "Maximum current per input phase in A; should last at least [stpkdr] MilliSeconds before triggering an alert."
  },
  "inputCTratio": {
    "name": "inputCTratio",
    "oid": "1.3.6.1.4.1.31034.2.8.1.12",
    "nodetype": "column",
    "class": "objecttype",
    "syntax": {
      "type": "Integer32",
      "class": "type"
    },
    "maxaccess": "read-write",
    "status": "current",
    "description": "The multiplier to use in case of use of /5 current transformers. Defaults to 1."
  },
  "inputName": {
    "name": "inputName",
    "oid": "1.3.6.1.4.1.31034.2.8.1.13",
    "nodetype": "column",
    "class": "objecttype",
    "syntax": {
      "type": "DisplayString",
      "class": "type"
    },
    "maxaccess": "read-write",
    "status": "current",
    "description": "User configurable naming of inputs or phases. Useful if channels are used to measure branches.."
  },
  "outletsTable": {
    "name": "outletsTable",
    "oid": "1.3.6.1.4.1.31034.2.9",
    "nodetype": "table",
    "class": "objecttype",
    "maxaccess": "not-accessible",
    "status": "current",
    "description": "This table contains the customer specific settings, determining toutlestablehe behaviour of the DEVICE."
  },
  "outletsEntry": {
    "name": "outletsEntry",
    "oid": "1.3.6.1.4.1.31034.2.9.1",
    "nodetype": "row",
    "class": "objecttype",
    "maxaccess": "not-accessible",
    "indices": [
      {
        "module": "SDEVICE-MIB",
        "object": "channelIndex4",
        "implied": 0
      }
    ],
    "status": "current",
    "description": "The record containing the registers forthe channel selected by channelIndex."
  },
  "channelIndex4": {
    "name": "channelIndex4",
    "oid": "1.3.6.1.4.1.31034.2.9.1.1",
    "nodetype": "column",
    "class": "objecttype",
    "syntax": {
      "type": "Integer32",
      "class": "type",
      "constraints": {
        "range": [
          {
            "min": 1,
            "max": 48
          }
        ]
      }
    },
    "maxaccess": "not-accessible",
    "status": "current",
    "description": "The channel. Its value ranges between 1 and 48, depending on the number of channels, usually 1."
  },
  "outletName": {
    "name": "outletName",
    "oid": "1.3.6.1.4.1.31034.2.9.1.2",
    "nodetype": "column",
    "class": "objecttype",
    "syntax": {
      "type": "DisplayString",
      "class": "type"
    },
    "maxaccess": "read-only",
    "status": "current",
    "description": "User configurable naming of individual outlets. Useful to distinguish outlets based on customer or device name."
  },
  "outputmeasuresTable": {
    "name": "outputmeasuresTable",
    "oid": "1.3.6.1.4.1.31034.2.10",
    "nodetype": "table",
    "class": "objecttype",
    "maxaccess": "not-accessible",
    "status": "current",
    "description": "This table contains all measures related to the measured outputs of the DEVICE. Note: up to 48 channels, depending on number of measured outlets."
  },
  "outputmeasuresEntry": {
    "name": "outputmeasuresEntry",
    "oid": "1.3.6.1.4.1.31034.2.10.1",
    "nodetype": "row",
    "class": "objecttype",
    "maxaccess": "not-accessible",
    "indices": [
      {
        "module": "SDEVICE-MIB",
        "object": "channelIndex7",
        "implied": 0
      }
    ],
    "status": "current",
    "description": "The record containing the registers for the channel selected by channelIndex."
  },
  "channelIndex7": {
    "name": "channelIndex7",
    "oid": "1.3.6.1.4.1.31034.2.10.1.1",
    "nodetype": "column",
    "class": "objecttype",
    "syntax": {
      "type": "Integer32",
      "class": "type",
      "constraints": {
        "range": [
          {
            "min": 1,
            "max": 48
          }
        ]
      }
    },
    "maxaccess": "not-accessible",
    "status": "current",
    "description": "The channel. Its value ranges between 1 and 48, depending on the number of channels, usually 1."
  },
  "kWhTotalO": {
    "name": "kWhTotalO",
    "oid": "1.3.6.1.4.1.31034.2.10.1.2",
    "nodetype": "column",
    "class": "objecttype",
    "syntax": {
      "type": "KiloWattHour",
      "class": "type"
    },
    "maxaccess": "read-only",
    "status": "current",
    "description": "Total kWh of selected output."
  },
  "kWhSubtotalO": {
    "name": "kWhSubtotalO",
    "oid": "1.3.6.1.4.1.31034.2.10.1.3",
    "nodetype": "column",
    "class": "objecttype",
    "syntax": {
      "type": "KiloWattHour",
      "class": "type"
    },
    "maxaccess": "read-only",
    "status": "current",
    "description": "kWh subtotal register of selected output. Reset to zero with [rsomks]."
  },
  "powerFactorO": {
    "name": "powerFactorO",
    "oid": "1.3.6.1.4.1.31034.2.10.1.4",
    "nodetype": "column",
    "class": "objecttype",
    "syntax": {
      "type": "DeciPowerFactor",
      "class": "type"
    },
    "maxaccess": "read-only",
    "status": "current",
    "description": "Power factor of output."
  },
  "actualCurrentO": {
    "name": "actualCurrentO",
    "oid": "1.3.6.1.4.1.31034.2.10.1.5",
    "nodetype": "column",
    "class": "objecttype",
    "syntax": {
      "type": "DeciAmps",
      "class": "type"
    },
    "maxaccess": "read-only",
    "status": "current",
    "description": "Actual apparent, RMS current."
  },
  "peakCurrentO": {
    "name": "peakCurrentO",
    "oid": "1.3.6.1.4.1.31034.2.10.1.6",
    "nodetype": "column",
    "class": "objecttype",
    "syntax": {
      "type": "DeciAmps",
      "class": "type"
    },
    "maxaccess": "read-only",
    "status": "current",
    "description": "Peak apparent, RMS current; highest value since last reset of alerts."
  },
  "actualVoltageO": {
    "name": "actualVoltageO",
    "oid": "1.3.6.1.4.1.31034.2.10.1.7",
    "nodetype": "column",
    "class": "objecttype",
    "syntax": {
      "type": "DeciVolts",
      "class": "type"
    },
    "maxaccess": "read-only",
    "status": "current",
    "description": "Actual voltage on output."
  },
  "maxOutletAmps": {
    "name": "maxOutletAmps",
    "oid": "1.3.6.1.4.1.31034.2.10.1.8",
    "nodetype": "column",
    "class": "objecttype",
    "syntax": {
      "type": "DeciAmps",
      "class": "type"
    },
    "maxaccess": "read-write",
    "status": "current",
    "description": "Maximum current per outlet in A; should last at least [stpkdr] MilliSeconds before triggering an alert."
  },
  "outputCTratio": {
    "name": "outputCTratio",
    "oid": "1.3.6.1.4.1.31034.2.10.1.9",
    "nodetype": "column",
    "class": "objecttype",
    "syntax": {
      "type": "Integer32",
      "class": "type"
    },
    "maxaccess": "read-write",
    "status": "current",
    "description": "The multiplier to use in case of use of /5 current transformers. Defaults to 1."
  },
  "switchedoutletsTable": {
    "name": "switchedoutletsTable",
    "oid": "1.3.6.1.4.1.31034.2.11",
    "nodetype": "table",
    "class": "objecttype",
    "maxaccess": "not-accessible",
    "status": "current",
    "description": "This table contains the current status of switchable DEVICE's."
  },
  "switchedoutletsEntry": {
    "name": "switchedoutletsEntry",
    "oid": "1.3.6.1.4.1.31034.2.11.1",
    "nodetype": "row",
    "class": "objecttype",
    "maxaccess": "not-accessible",
    "indices": [
      {
        "module": "SDEVICE-MIB",
        "object": "channelIndex5",
        "implied": 0
      }
    ],
    "status": "current",
    "description": "The record containing the registers for the channel selected by channelIndex."
  },
  "channelIndex5": {
    "name": "channelIndex5",
    "oid": "1.3.6.1.4.1.31034.2.11.1.1",
    "nodetype": "column",
    "class": "objecttype",
    "syntax": {
      "type": "Integer32",
      "class": "type",
      "constraints": {
        "range": [
          {
            "min": 1,
            "max": 48
          }
        ]
      }
    },
    "maxaccess": "not-accessible",
    "status": "current",
    "description": "The channel. Its value ranges between 1 and 48, depending on the number of channels, usually 1."
  },
  "currentState": {
    "name": "currentState",
    "oid": "1.3.6.1.4.1.31034.2.11.1.2",
    "nodetype": "column",
    "class": "objecttype",
    "syntax": {
      "type": "Integer32",
      "class": "type",
      "constraints": {
        "range": [
          {
            "min": 0,
            "max": 1
          }
        ]
      }
    },
    "maxaccess": "read-write",
    "status": "current",
    "description": "The actual state of the outlet relays. The hardware will contain max 48 outlets. Writing is only effective after setting [swounl]."
  },
  "scheduled": {
    "name": "scheduled",
    "oid": "1.3.6.1.4.1.31034.2.11.1.3",
    "nodetype": "column",
    "class": "objecttype",
    "syntax": {
      "type": "Integer32",
      "class": "type",
      "constraints": {
        "range": [
          {
            "min": 0,
            "max": 1
          }
        ]
      }
    },
    "maxaccess": "read-only",
    "status": "current",
    "description": "A one indicates pending activity; the switch delay has not yet expired."
  },
  "unlock": {
    "name": "unlock",
    "oid": "1.3.6.1.4.1.31034.2.11.1.4",
    "nodetype": "column",
    "class": "objecttype",
    "syntax": {
      "type": "Integer32",
      "class": "type"
    },
    "maxaccess": "read-write",
    "status": "current",
    "description": "Setting the value to one will release the safety for this outlet for a couple seconds; switching and rebooting are then temporarily enabled."
  },
  "individualOutletDelay": {
    "name": "individualOutletDelay",
    "oid": "1.3.6.1.4.1.31034.2.11.1.5",
    "nodetype": "column",
    "class": "objecttype",
    "syntax": {
      "type": "Seconds",
      "class": "type"
    },
    "maxaccess": "read-write",
    "status": "current",
    "description": "Delay before an individual outlet switches on at power-up in Seconds."
  },
  "sensorTable": {
    "name": "sensorTable",
    "oid": "1.3.6.1.4.1.31034.2.12",
    "nodetype": "table",
    "class": "objecttype",
    "maxaccess": "not-accessible",
    "status": "current",
    "description": "This table contains the environmental measurements. As well internal temperature as external temperature probes."
  },
  "sensorEntry": {
    "name": "sensorEntry",
    "oid": "1.3.6.1.4.1.31034.2.12.1",
    "nodetype": "row",
    "class": "objecttype",
    "maxaccess": "not-accessible",
    "indices": [
      {
        "module": "SDEVICE-MIB",
        "object": "channelIndex8",
        "implied": 0
      }
    ],
    "status": "current",
    "description": "The record containing the registers for the channel selected by channelIndex."
  },
  "channelIndex8": {
    "name": "channelIndex8",
    "oid": "1.3.6.1.4.1.31034.2.12.1.1",
    "nodetype": "column",
    "class": "objecttype",
    "syntax": {
      "type": "Integer32",
      "class": "type",
      "constraints": {
        "range": [
          {
            "min": 1,
            "max": 48
          }
        ]
      }
    },
    "maxaccess": "not-accessible",
    "status": "current",
    "description": "The channel. Its value ranges between 1 and 48, depending on the number of channels, usually 1."
  },
  "sensorType": {
    "name": "sensorType",
    "oid": "1.3.6.1.4.1.31034.2.12.1.2",
    "nodetype": "column",
    "class": "objecttype",
    "syntax": {
      "type": "DisplayString",
      "class": "type"
    },
    "maxaccess": "read-only",
    "status": "current",
    "description": "Type of connected sensor, either T, H or I for respectively Temperature (C), Humidity (%) or dry switch contact"
  },
  "sensorValue": {
    "name": "sensorValue",
    "oid": "1.3.6.1.4.1.31034.2.12.1.3",
    "nodetype": "column",
    "class": "objecttype",
    "syntax": {
      "type": "DeciValue",
      "class": "type"
    },
    "maxaccess": "read-only",
    "status": "current",
    "description": "Value of connected sensor"
  },
  "sensorName": {
    "name": "sensorName",
    "oid": "1.3.6.1.4.1.31034.2.12.1.4",
    "nodetype": "column",
    "class": "objecttype",
    "syntax": {
      "type": "DisplayString",
      "class": "type"
    },
    "maxaccess": "read-write",
    "status": "current",
    "description": "User definable name for sensors."
  },
  "conformance": {
    "name": "conformance",
    "oid": "1.3.6.1.4.1.31034.99",
    "class": "objectidentity"
  },
  "compliances": {
    "name": "compliances",
    "oid": "1.3.6.1.4.1.31034.99.1",
    "class": "objectidentity"
  },
  "compliance": {
    "name": "compliance",
    "oid": "1.3.6.1.4.1.31034.99.1.1",
    "class": "modulecompliance",
    "modulecompliance": [
      {
        "object": "sensorsGroup",
        "module": "SDEVICE-MIB"
      },
      {
        "object": "outputMeasuresGroup",
        "module": "SDEVICE-MIB"
      },
      {
        "object": "inputMeasuresGroup",
        "module": "SDEVICE-MIB"
      },
      {
        "object": "switchedOutletsGroup",
        "module": "SDEVICE-MIB"
      },
      {
        "object": "settingsGroup",
        "module": "SDEVICE-MIB"
      },
      {
        "object": "systemStatusGroup",
        "module": "SDEVICE-MIB"
      },
      {
        "object": "configurationGroup",
        "module": "SDEVICE-MIB"
      },
      {
        "object": "identificationGroup",
        "module": "SDEVICE-MIB"
      },
      {
        "object": "resetGroup",
        "module": "SDEVICE-MIB"
      }
    ],
    "status": "current",
    "description": "The requirements for conformance to the SPGW-MIB."
  },
  "groups": {
    "name": "groups",
    "oid": "1.3.6.1.4.1.31034.99.2",
    "class": "objectidentity"
  },
  "identificationGroup": {
    "name": "identificationGroup",
    "oid": "1.3.6.1.4.1.31034.99.2.1",
    "class": "objectgroup",
    "objects": [
      {
        "module": "SDEVICE-MIB",
        "object": "spdmVersion"
      },
      {
        "module": "SDEVICE-MIB",
        "object": "firmwareVersion"
      },
      {
        "module": "SDEVICE-MIB",
        "object": "salesOrderNumber"
      },
      {
        "module": "SDEVICE-MIB",
        "object": "productId"
      },
      {
        "module": "SDEVICE-MIB",
        "object": "serialNumber"
      },
      {
        "module": "SDEVICE-MIB",
        "object": "hardwareAddress"
      },
      {
        "module": "SDEVICE-MIB",
        "object": "unitAddress"
      },
      {
        "module": "SDEVICE-MIB",
        "object": "deviceName"
      },
      {
        "module": "SDEVICE-MIB",
        "object": "deviceLocation"
      },
      {
        "module": "SDEVICE-MIB",
        "object": "vanityTag"
      },
      {
        "module": "SDEVICE-MIB",
        "object": "macAddress"
      },
      {
        "module": "SDEVICE-MIB",
        "object": "buildNumber"
      }
    ],
    "status": "current",
    "description": "A collection of objects providing identification information about the device."
  },
  "configurationGroup": {
    "name": "configurationGroup",
    "oid": "1.3.6.1.4.1.31034.99.2.2",
    "class": "objectgroup",
    "objects": [
      {
        "module": "SDEVICE-MIB",
        "object": "noPhases"
      },
      {
        "module": "SDEVICE-MIB",
        "object": "noOutletsTotal"
      },
      {
        "module": "SDEVICE-MIB",
        "object": "noSwitchedOutlets"
      },
      {
        "module": "SDEVICE-MIB",
        "object": "noMeasuredOutlets"
      },
      {
        "module": "SDEVICE-MIB",
        "object": "maximumLoad"
      },
      {
        "module": "SDEVICE-MIB",
        "object": "noSensors"
      }
    ],
    "status": "current",
    "description": "A collection of objects providing configuration information about the device."
  },
  "systemStatusGroup": {
    "name": "systemStatusGroup",
    "oid": "1.3.6.1.4.1.31034.99.2.3",
    "class": "objectgroup",
    "objects": [
      {
        "module": "SDEVICE-MIB",
        "object": "deviceStatusCode"
      },
      {
        "module": "SDEVICE-MIB",
        "object": "temperatureAlert"
      },
      {
        "module": "SDEVICE-MIB",
        "object": "inputCurrentAlert"
      },
      {
        "module": "SDEVICE-MIB",
        "object": "outputCurrentAlert"
      },
      {
        "module": "SDEVICE-MIB",
        "object": "inputVoltageAlert"
      },
      {
        "module": "SDEVICE-MIB",
        "object": "oCurrentDropAlert"
      },
      {
        "module": "SDEVICE-MIB",
        "object": "iCurrentDropAlert"
      }
    ],
    "status": "current",
    "description": "A collection of objects providing status information about the device."
  },
  "resetGroup": {
    "name": "resetGroup",
    "oid": "1.3.6.1.4.1.31034.99.2.4",
    "class": "objectgroup",
    "objects": [
      {
        "module": "SDEVICE-MIB",
        "object": "resetAlerts"
      },
      {
        "module": "SDEVICE-MIB",
        "object": "resetPeakValues"
      },
      {
        "module": "SDEVICE-MIB",
        "object": "rebootDevice"
      },
      {
        "module": "SDEVICE-MIB",
        "object": "zeroInputKWhSubtotal"
      },
      {
        "module": "SDEVICE-MIB",
        "object": "zeroOutKWhSubtotal"
      }
    ],
    "status": "current",
    "description": "Groups resettable attributes op the device."
  },
  "settingsGroup": {
    "name": "settingsGroup",
    "oid": "1.3.6.1.4.1.31034.99.2.5",
    "class": "objectgroup",
    "objects": [
      {
        "module": "SDEVICE-MIB",
        "object": "peakDuration"
      },
      {
        "module": "SDEVICE-MIB",
        "object": "localAlertReset"
      },
      {
        "module": "SDEVICE-MIB",
        "object": "fixedOutletDelay"
      },
      {
        "module": "SDEVICE-MIB",
        "object": "powerSaverMode"
      },
      {
        "module": "SDEVICE-MIB",
        "object": "outletPowerupMode"
      },
      {
        "module": "SDEVICE-MIB",
        "object": "maximumTemperature"
      },
      {
        "module": "SDEVICE-MIB",
        "object": "displayOrientation"
      },
      {
        "module": "SDEVICE-MIB",
        "object": "maxInletAmps"
      },
      {
        "module": "SDEVICE-MIB",
        "object": "maxOutletAmps"
      },
      {
        "module": "SDEVICE-MIB",
        "object": "outputCTratio"
      },
      {
        "module": "SDEVICE-MIB",
        "object": "inputCTratio"
      },
      {
        "module": "SDEVICE-MIB",
        "object": "inputName"
      },
      {
        "module": "SDEVICE-MIB",
        "object": "outletName"
      },
      {
        "module": "SDEVICE-MIB",
        "object": "individualOutletDelay"
      },
      {
        "module": "SDEVICE-MIB",
        "object": "currentDropDetection"
      },
      {
        "module": "SDEVICE-MIB",
        "object": "wirelessDisplayPower"
      }
    ],
    "status": "current",
    "description": "A collection of objects providing the actual settings about the device."
  },
  "switchedOutletsGroup": {
    "name": "switchedOutletsGroup",
    "oid": "1.3.6.1.4.1.31034.99.2.6",
    "class": "objectgroup",
    "objects": [
      {
        "module": "SDEVICE-MIB",
        "object": "currentState"
      },
      {
        "module": "SDEVICE-MIB",
        "object": "scheduled"
      },
      {
        "module": "SDEVICE-MIB",
        "object": "individualOutletDelay"
      },
      {
        "module": "SDEVICE-MIB",
        "object": "unlock"
      }
    ],
    "status": "current",
    "description": "A collection of objects providing the actual outlet status of the device."
  },
  "inputMeasuresGroup": {
    "name": "inputMeasuresGroup",
    "oid": "1.3.6.1.4.1.31034.99.2.7",
    "class": "objectgroup",
    "objects": [
      {
        "module": "SDEVICE-MIB",
        "object": "kWhTotalI"
      },
      {
        "module": "SDEVICE-MIB",
        "object": "kWhSubtotalI"
      },
      {
        "module": "SDEVICE-MIB",
        "object": "powerFactorI"
      },
      {
        "module": "SDEVICE-MIB",
        "object": "actualCurrentI"
      },
      {
        "module": "SDEVICE-MIB",
        "object": "peakCurrentI"
      },
      {
        "module": "SDEVICE-MIB",
        "object": "actualVoltageI"
      },
      {
        "module": "SDEVICE-MIB",
        "object": "minVoltageI"
      },
      {
        "module": "SDEVICE-MIB",
        "object": "powerWattI"
      },
      {
        "module": "SDEVICE-MIB",
        "object": "powerVAI"
      },
      {
        "module": "SDEVICE-MIB",
        "object": "maxInletAmps"
      },
      {
        "module": "SDEVICE-MIB",
        "object": "inputCTratio"
      },
      {
        "module": "SDEVICE-MIB",
        "object": "inputName"
      }
    ],
    "status": "current",
    "description": "A collection of objects providing the actual input measurements of the device."
  },
  "outputMeasuresGroup": {
    "name": "outputMeasuresGroup",
    "oid": "1.3.6.1.4.1.31034.99.2.8",
    "class": "objectgroup",
    "objects": [
      {
        "module": "SDEVICE-MIB",
        "object": "kWhTotalO"
      },
      {
        "module": "SDEVICE-MIB",
        "object": "kWhSubtotalO"
      },
      {
        "module": "SDEVICE-MIB",
        "object": "powerFactorO"
      },
      {
        "module": "SDEVICE-MIB",
        "object": "actualCurrentO"
      },
      {
        "module": "SDEVICE-MIB",
        "object": "peakCurrentO"
      },
      {
        "module": "SDEVICE-MIB",
        "object": "actualVoltageO"
      },
      {
        "module": "SDEVICE-MIB",
        "object": "maxOutletAmps"
      },
      {
        "module": "SDEVICE-MIB",
        "object": "outputCTratio"
      }
    ],
    "status": "current",
    "description": "A collection of objects providing the actual output measurements of the device."
  },
  "sensorsGroup": {
    "name": "sensorsGroup",
    "oid": "1.3.6.1.4.1.31034.99.2.9",
    "class": "objectgroup",
    "objects": [
      {
        "module": "SDEVICE-MIB",
        "object": "sensorType"
      },
      {
        "module": "SDEVICE-MIB",
        "object": "sensorValue"
      },
      {
        "module": "SDEVICE-MIB",
        "object": "sensorName"
      }
    ],
    "status": "current",
    "description": "A collection of objects providing the actual environmental measurements of the device."
  },
  "meta": {
    "comments": [
      "ASN.1 source file:///Users/neermitt/kusanagi/mibs.snmplabs.com/asn1/SDEVICE-MIB",
      "Produced by pysmi-0.3.4 at Fri May 24 21:25:08 2019",
      "On host NEERMITT-M-J0NV platform Darwin version 18.6.0 by user neermitt",
      "Using Python version 3.7.3 (default, Mar 27 2019, 09:23:15) "
    ],
    "module": "SDEVICE-MIB"
  }
}