{
  "imports": {
    "class": "imports",
    "SNMPv2-CONF": [
      "NOTIFICATION-GROUP",
      "MODULE-COMPLIANCE"
    ],
    "SNMPv2-SMI": [
      "iso",
      "OBJECT-TYPE",
      "Bits",
      "MODULE-IDENTITY",
      "Gauge32",
      "Counter64",
      "NOTIFICATION-TYPE",
      "IpAddress",
      "MibIdentifier",
      "Integer32",
      "Unsigned32",
      "TimeTicks",
      "Counter32",
      "OBJECT-IDENTITY"
    ],
    "SNMPv2-TC": [
      "DisplayString",
      "TEXTUAL-CONVENTION"
    ],
    "TPT-TPAMIBS-MIB": [
      "tpt-tpa-eventsV2",
      "tpt-tpa-objs",
      "tpt-tpa-unkparams"
    ]
  },
  "tpt_resource": {
    "name": "tpt_resource",
    "oid": "1.3.6.1.4.1.10734.3.3.2.5",
    "class": "moduleidentity",
    "revisions": [
      {
        "revision": "2016-05-25 18:54",
        "description": "Updated copyright information. Minor MIB syntax fixes."
      }
    ],
    "lastupdated": "201605251854Z",
    "organization": "Trend Micro, Inc.",
    "contactinfo": "www.trendmicro.com",
    "description": "Resource consumption and threshold notifications. Copyright (C) 2016 Trend Micro Incorporated. All Rights Reserved. Trend Micro makes no warranty of any kind with regard to this material, including, but not limited to, the implied warranties of merchantability and fitness for a particular purpose. Trend Micro shall not be liable for errors contained herein or for incidental or consequential damages in connection with the furnishing, performance, or use of this material. This document contains proprietary information, which is protected by copyright. No part of this document may be photocopied, reproduced, or translated into another language without the prior written consent of Trend Micro. The information is provided 'as is' without warranty of any kind and is subject to change without notice. The only warranties for Trend Micro products and services are set forth in the express warranty statements accompanying such products and services. Nothing herein should be construed as constituting an additional warranty. Trend Micro shall not be liable for technical or editorial errors or omissions contained herein. TippingPoint(R), the TippingPoint logo, and Digital Vaccine(R) are registered trademarks of Trend Micro. All other company and product names may be trademarks of their respective holders. All rights reserved. This document contains confidential information, trade secrets or both, which are the property of Trend Micro. No part of this documentation may be reproduced in any form or by any means or used to make any derivative work (such as translation, transformation, or adaptation) without written permission from Trend Micro or one of its subsidiaries. All other company and product names may be trademarks of their respective holders. "
  },
  "ResourceIdentifier": {
    "name": "ResourceIdentifier",
    "class": "textualconvention",
    "type": {
      "type": "INTEGER",
      "class": "type",
      "constraints": {
        "enumeration": {
          "filesystem": 1,
          "hpCPU": 2,
          "hpMemory": 3,
          "chassisTemp": 4,
          "fan": 5,
          "powerSupply": 6,
          "hardDisk": 7,
          "i2cBus": 8
        }
      }
    },
    "status": "current",
    "description": "An identifier of the resource parameter pertaining to a notification."
  },
  "ResourceState": {
    "name": "ResourceState",
    "class": "textualconvention",
    "type": {
      "type": "INTEGER",
      "class": "type",
      "constraints": {
        "enumeration": {
          "unknown": 0,
          "red": 1,
          "yellow": 2,
          "green": 3
        }
      }
    },
    "status": "current",
    "description": "A selection from a set of state levels used in resource thresholds."
  },
  "PowerSupplyState": {
    "name": "PowerSupplyState",
    "class": "textualconvention",
    "type": {
      "type": "INTEGER",
      "class": "type",
      "constraints": {
        "enumeration": {
          "unknown": 0,
          "red": 1,
          "green": 2
        }
      }
    },
    "status": "current",
    "description": "A selection from a set of state levels used in power supply status."
  },
  "SnmpVersions": {
    "name": "SnmpVersions",
    "class": "textualconvention",
    "type": {
      "type": "INTEGER",
      "class": "type",
      "constraints": {
        "enumeration": {
          "none": 0,
          "snmpv2": 1,
          "snmpv3": 2,
          "snmpv2-and-snmpv3": 3
        }
      }
    },
    "status": "current",
    "description": "An indicator of which SNMP versions are enabled."
  },
  "EnabledOrNot": {
    "name": "EnabledOrNot",
    "class": "textualconvention",
    "type": {
      "type": "INTEGER",
      "class": "type",
      "constraints": {
        "enumeration": {
          "disabled": 0,
          "enabled": 1
        }
      }
    },
    "status": "current",
    "description": "An indication of whether a feature is configured as enabled or disabled."
  },
  "FilesystemState": {
    "name": "FilesystemState",
    "class": "textualconvention",
    "type": {
      "type": "INTEGER",
      "class": "type",
      "constraints": {
        "enumeration": {
          "unformatted": 0,
          "formatted": 1,
          "mounted": 2
        }
      }
    },
    "status": "current",
    "description": "Current state of the filesystem."
  },
  "RemoteAuthType": {
    "name": "RemoteAuthType",
    "class": "textualconvention",
    "type": {
      "type": "INTEGER",
      "class": "type",
      "constraints": {
        "enumeration": {
          "none": 0,
          "radius": 1,
          "sms": 2,
          "tacacs": 3
        }
      }
    },
    "status": "current",
    "description": "An indication of which remote authentication are enabled."
  },
  "resourceNumberOfFilesystems": {
    "name": "resourceNumberOfFilesystems",
    "oid": "1.3.6.1.4.1.10734.3.3.2.5.1",
    "nodetype": "scalar",
    "class": "objecttype",
    "syntax": {
      "type": "Unsigned32",
      "class": "type"
    },
    "maxaccess": "read-only",
    "status": "current",
    "description": "The number of filesystems on the device's hard disk."
  },
  "resourceFSTable": {
    "name": "resourceFSTable",
    "oid": "1.3.6.1.4.1.10734.3.3.2.5.2",
    "nodetype": "table",
    "class": "objecttype",
    "maxaccess": "not-accessible",
    "status": "current",
    "description": "Table of per-filesystem resource information."
  },
  "resourceFSEntry": {
    "name": "resourceFSEntry",
    "oid": "1.3.6.1.4.1.10734.3.3.2.5.2.1",
    "nodetype": "row",
    "class": "objecttype",
    "maxaccess": "not-accessible",
    "indices": [
      {
        "module": "TPT-RESOURCE-MIB",
        "object": "resourceFSIndex",
        "implied": 0
      }
    ],
    "status": "current",
    "description": "An entry in the resource filesystem table. Rows cannot be created or deleted. "
  },
  "resourceFSInUseMB": {
    "name": "resourceFSInUseMB",
    "oid": "1.3.6.1.4.1.10734.3.3.2.5.2.1.1",
    "nodetype": "column",
    "class": "objecttype",
    "syntax": {
      "type": "Integer32",
      "class": "type"
    },
    "maxaccess": "read-only",
    "status": "current",
    "description": "The number of MB in use for this filesystem."
  },
  "resourceFSThresholdMaj": {
    "name": "resourceFSThresholdMaj",
    "oid": "1.3.6.1.4.1.10734.3.3.2.5.2.1.2",
    "nodetype": "column",
    "class": "objecttype",
    "syntax": {
      "type": "Integer32",
      "class": "type"
    },
    "maxaccess": "read-only",
    "status": "current",
    "description": "The major threshold value (percent) in use for this filesystem."
  },
  "resourceFSThresholdCrit": {
    "name": "resourceFSThresholdCrit",
    "oid": "1.3.6.1.4.1.10734.3.3.2.5.2.1.3",
    "nodetype": "column",
    "class": "objecttype",
    "syntax": {
      "type": "Integer32",
      "class": "type"
    },
    "maxaccess": "read-only",
    "status": "current",
    "description": "The critical threshold value (percent) in use for this filesystem."
  },
  "resourceFSRangeMin": {
    "name": "resourceFSRangeMin",
    "oid": "1.3.6.1.4.1.10734.3.3.2.5.2.1.4",
    "nodetype": "column",
    "class": "objecttype",
    "syntax": {
      "type": "Integer32",
      "class": "type"
    },
    "maxaccess": "read-only",
    "status": "current",
    "description": "The minimum value of the range of MB in use (usually zero)."
  },
  "resourceFSRangeMax": {
    "name": "resourceFSRangeMax",
    "oid": "1.3.6.1.4.1.10734.3.3.2.5.2.1.5",
    "nodetype": "column",
    "class": "objecttype",
    "syntax": {
      "type": "Integer32",
      "class": "type"
    },
    "maxaccess": "read-only",
    "status": "current",
    "description": "The size (in MB) of this filesystem."
  },
  "resourceFSName": {
    "name": "resourceFSName",
    "oid": "1.3.6.1.4.1.10734.3.3.2.5.2.1.6",
    "nodetype": "column",
    "class": "objecttype",
    "syntax": {
      "type": "OCTET STRING",
      "class": "type",
      "constraints": {
        "size": [
          {
            "min": 0,
            "max": 40
          }
        ]
      }
    },
    "maxaccess": "read-only",
    "status": "current",
    "description": "The name of this filesystem."
  },
  "resourceFSIndex": {
    "name": "resourceFSIndex",
    "oid": "1.3.6.1.4.1.10734.3.3.2.5.2.1.7",
    "nodetype": "column",
    "class": "objecttype",
    "syntax": {
      "type": "Unsigned32",
      "class": "type"
    },
    "maxaccess": "not-accessible",
    "status": "current",
    "description": "The number of this table row, from one to the number of filesystems."
  },
  "resourceFSState": {
    "name": "resourceFSState",
    "oid": "1.3.6.1.4.1.10734.3.3.2.5.2.1.8",
    "nodetype": "column",
    "class": "objecttype",
    "syntax": {
      "type": "FilesystemState",
      "class": "type"
    },
    "maxaccess": "read-only",
    "status": "current",
    "description": "Current state of the filesystem."
  },
  "resourceFSEncryption": {
    "name": "resourceFSEncryption",
    "oid": "1.3.6.1.4.1.10734.3.3.2.5.2.1.9",
    "nodetype": "column",
    "class": "objecttype",
    "syntax": {
      "type": "EnabledOrNot",
      "class": "type"
    },
    "maxaccess": "read-only",
    "status": "current",
    "description": "Indicates whether this filesystem is encrypted or not."
  },
  "resourceHPMemoryObjs": {
    "name": "resourceHPMemoryObjs",
    "oid": "1.3.6.1.4.1.10734.3.3.2.5.3",
    "class": "objectidentity",
    "status": "current",
    "description": "Sub-tree of host processor memory information."
  },
  "resourceHPMemoryInUsePercent": {
    "name": "resourceHPMemoryInUsePercent",
    "oid": "1.3.6.1.4.1.10734.3.3.2.5.3.1",
    "nodetype": "scalar",
    "class": "objecttype",
    "syntax": {
      "type": "Integer32",
      "class": "type"
    },
    "maxaccess": "read-only",
    "status": "current",
    "description": "The percentage of host processor memory in use."
  },
  "resourceHPMemoryThresholdMaj": {
    "name": "resourceHPMemoryThresholdMaj",
    "oid": "1.3.6.1.4.1.10734.3.3.2.5.3.2",
    "nodetype": "scalar",
    "class": "objecttype",
    "syntax": {
      "type": "Integer32",
      "class": "type"
    },
    "maxaccess": "read-only",
    "status": "current",
    "description": "The major threshold value for host processor memory in use."
  },
  "resourceHPMemoryThresholdCrit": {
    "name": "resourceHPMemoryThresholdCrit",
    "oid": "1.3.6.1.4.1.10734.3.3.2.5.3.3",
    "nodetype": "scalar",
    "class": "objecttype",
    "syntax": {
      "type": "Integer32",
      "class": "type"
    },
    "maxaccess": "read-only",
    "status": "current",
    "description": "The critical threshold value for host processor memory in use."
  },
  "resourceHPMemoryRangeMin": {
    "name": "resourceHPMemoryRangeMin",
    "oid": "1.3.6.1.4.1.10734.3.3.2.5.3.4",
    "nodetype": "scalar",
    "class": "objecttype",
    "syntax": {
      "type": "Integer32",
      "class": "type"
    },
    "maxaccess": "read-only",
    "status": "current",
    "description": "The minimum percentage of host processor memory in use (usually zero)."
  },
  "resourceHPMemoryRangeMax": {
    "name": "resourceHPMemoryRangeMax",
    "oid": "1.3.6.1.4.1.10734.3.3.2.5.3.5",
    "nodetype": "scalar",
    "class": "objecttype",
    "syntax": {
      "type": "Integer32",
      "class": "type"
    },
    "maxaccess": "read-only",
    "status": "current",
    "description": "The maximum percentage of host processor memory in use (usually 100)."
  },
  "resourceHPMemoryTotal": {
    "name": "resourceHPMemoryTotal",
    "oid": "1.3.6.1.4.1.10734.3.3.2.5.3.6",
    "nodetype": "scalar",
    "class": "objecttype",
    "syntax": {
      "type": "Unsigned32",
      "class": "type"
    },
    "maxaccess": "read-only",
    "status": "current",
    "description": "The size (in bytes) of host processor memory."
  },
  "resourceHPCPUObjs": {
    "name": "resourceHPCPUObjs",
    "oid": "1.3.6.1.4.1.10734.3.3.2.5.4",
    "class": "objectidentity",
    "status": "current",
    "description": "Sub-tree of host processor CPU information."
  },
  "resourceHPCPUBusyPercent": {
    "name": "resourceHPCPUBusyPercent",
    "oid": "1.3.6.1.4.1.10734.3.3.2.5.4.1",
    "nodetype": "scalar",
    "class": "objecttype",
    "syntax": {
      "type": "Integer32",
      "class": "type"
    },
    "maxaccess": "read-only",
    "status": "current",
    "description": "The percentage of host processor CPU busy."
  },
  "resourceHPCPUThresholdMaj": {
    "name": "resourceHPCPUThresholdMaj",
    "oid": "1.3.6.1.4.1.10734.3.3.2.5.4.2",
    "nodetype": "scalar",
    "class": "objecttype",
    "syntax": {
      "type": "Integer32",
      "class": "type"
    },
    "maxaccess": "read-only",
    "status": "current",
    "description": "The major threshold value for host processor CPU busy."
  },
  "resourceHPCPUThresholdCrit": {
    "name": "resourceHPCPUThresholdCrit",
    "oid": "1.3.6.1.4.1.10734.3.3.2.5.4.3",
    "nodetype": "scalar",
    "class": "objecttype",
    "syntax": {
      "type": "Integer32",
      "class": "type"
    },
    "maxaccess": "read-only",
    "status": "current",
    "description": "The critical threshold value for host processor CPU busy."
  },
  "resourceHPCPURangeMin": {
    "name": "resourceHPCPURangeMin",
    "oid": "1.3.6.1.4.1.10734.3.3.2.5.4.4",
    "nodetype": "scalar",
    "class": "objecttype",
    "syntax": {
      "type": "Integer32",
      "class": "type"
    },
    "maxaccess": "read-only",
    "status": "current",
    "description": "The minimum percentage of host processor CPU busy (usually zero)."
  },
  "resourceHPCPURangeMax": {
    "name": "resourceHPCPURangeMax",
    "oid": "1.3.6.1.4.1.10734.3.3.2.5.4.5",
    "nodetype": "scalar",
    "class": "objecttype",
    "syntax": {
      "type": "Integer32",
      "class": "type"
    },
    "maxaccess": "read-only",
    "status": "current",
    "description": "The maximum percentage of host processor CPU busy (usually 100)."
  },
  "resourceNPCPUBusyPercentA": {
    "name": "resourceNPCPUBusyPercentA",
    "oid": "1.3.6.1.4.1.10734.3.3.2.5.4.6",
    "nodetype": "scalar",
    "class": "objecttype",
    "syntax": {
      "type": "Integer32",
      "class": "type"
    },
    "maxaccess": "read-only",
    "status": "current",
    "description": "Total Utilization of XLR A"
  },
  "resourceNPCPUBusyPercentTier2A": {
    "name": "resourceNPCPUBusyPercentTier2A",
    "oid": "1.3.6.1.4.1.10734.3.3.2.5.4.7",
    "nodetype": "scalar",
    "class": "objecttype",
    "syntax": {
      "type": "Integer32",
      "class": "type"
    },
    "maxaccess": "read-only",
    "status": "current",
    "description": "F Thread Utilization of XLR A"
  },
  "resourceNPCPUBusyPercentTier3A": {
    "name": "resourceNPCPUBusyPercentTier3A",
    "oid": "1.3.6.1.4.1.10734.3.3.2.5.4.8",
    "nodetype": "scalar",
    "class": "objecttype",
    "syntax": {
      "type": "Integer32",
      "class": "type"
    },
    "maxaccess": "read-only",
    "status": "current",
    "description": "KS Thread Utilization of XLR A"
  },
  "resourceNPCPUBusyPercentTier4A": {
    "name": "resourceNPCPUBusyPercentTier4A",
    "oid": "1.3.6.1.4.1.10734.3.3.2.5.4.9",
    "nodetype": "scalar",
    "class": "objecttype",
    "syntax": {
      "type": "Integer32",
      "class": "type"
    },
    "maxaccess": "read-only",
    "status": "current",
    "description": "L Thread Utilization of XLR A"
  },
  "resourceNPCPUBusyPercentB": {
    "name": "resourceNPCPUBusyPercentB",
    "oid": "1.3.6.1.4.1.10734.3.3.2.5.4.10",
    "nodetype": "scalar",
    "class": "objecttype",
    "syntax": {
      "type": "Integer32",
      "class": "type"
    },
    "maxaccess": "read-only",
    "status": "current",
    "description": "Total Utilization of XLR B"
  },
  "resourceNPCPUBusyPercentTier2B": {
    "name": "resourceNPCPUBusyPercentTier2B",
    "oid": "1.3.6.1.4.1.10734.3.3.2.5.4.11",
    "nodetype": "scalar",
    "class": "objecttype",
    "syntax": {
      "type": "Integer32",
      "class": "type"
    },
    "maxaccess": "read-only",
    "status": "current",
    "description": "F Thread Utilization of XLR B"
  },
  "resourceNPCPUBusyPercentTier3B": {
    "name": "resourceNPCPUBusyPercentTier3B",
    "oid": "1.3.6.1.4.1.10734.3.3.2.5.4.12",
    "nodetype": "scalar",
    "class": "objecttype",
    "syntax": {
      "type": "Integer32",
      "class": "type"
    },
    "maxaccess": "read-only",
    "status": "current",
    "description": "KS Thread Utilization of XLR B"
  },
  "resourceNPCPUBusyPercentTier4B": {
    "name": "resourceNPCPUBusyPercentTier4B",
    "oid": "1.3.6.1.4.1.10734.3.3.2.5.4.13",
    "nodetype": "scalar",
    "class": "objecttype",
    "syntax": {
      "type": "Integer32",
      "class": "type"
    },
    "maxaccess": "read-only",
    "status": "current",
    "description": "L Thread Utilization of XLR B"
  },
  "resourceNPCPUBusyPercentC": {
    "name": "resourceNPCPUBusyPercentC",
    "oid": "1.3.6.1.4.1.10734.3.3.2.5.4.14",
    "nodetype": "scalar",
    "class": "objecttype",
    "syntax": {
      "type": "Integer32",
      "class": "type"
    },
    "maxaccess": "read-only",
    "status": "current",
    "description": "Total Utilization of XLR C"
  },
  "resourceNPCPUBusyPercentTier2C": {
    "name": "resourceNPCPUBusyPercentTier2C",
    "oid": "1.3.6.1.4.1.10734.3.3.2.5.4.15",
    "nodetype": "scalar",
    "class": "objecttype",
    "syntax": {
      "type": "Integer32",
      "class": "type"
    },
    "maxaccess": "read-only",
    "status": "current",
    "description": "F Thread Utilization of XLR C"
  },
  "resourceNPCPUBusyPercentTier3C": {
    "name": "resourceNPCPUBusyPercentTier3C",
    "oid": "1.3.6.1.4.1.10734.3.3.2.5.4.16",
    "nodetype": "scalar",
    "class": "objecttype",
    "syntax": {
      "type": "Integer32",
      "class": "type"
    },
    "maxaccess": "read-only",
    "status": "current",
    "description": "KS Thread Utilization of XLR C"
  },
  "resourceNPCPUBusyPercentTier4C": {
    "name": "resourceNPCPUBusyPercentTier4C",
    "oid": "1.3.6.1.4.1.10734.3.3.2.5.4.17",
    "nodetype": "scalar",
    "class": "objecttype",
    "syntax": {
      "type": "Integer32",
      "class": "type"
    },
    "maxaccess": "read-only",
    "status": "current",
    "description": "L Thread Utilization of XLR C"
  },
  "resourceChassisTempObjs": {
    "name": "resourceChassisTempObjs",
    "oid": "1.3.6.1.4.1.10734.3.3.2.5.5",
    "class": "objectidentity",
    "status": "current",
    "description": "Sub-tree of chassis temperature information."
  },
  "resourceChassisTempDegreesC": {
    "name": "resourceChassisTempDegreesC",
    "oid": "1.3.6.1.4.1.10734.3.3.2.5.5.1",
    "nodetype": "scalar",
    "class": "objecttype",
    "syntax": {
      "type": "Integer32",
      "class": "type"
    },
    "maxaccess": "read-only",
    "status": "current",
    "description": "The chassis temperature in degrees C."
  },
  "resourceChassisTempThresholdMaj": {
    "name": "resourceChassisTempThresholdMaj",
    "oid": "1.3.6.1.4.1.10734.3.3.2.5.5.2",
    "nodetype": "scalar",
    "class": "objecttype",
    "syntax": {
      "type": "Integer32",
      "class": "type"
    },
    "maxaccess": "read-only",
    "status": "current",
    "description": "The major threshold value for chassis temperature."
  },
  "resourceChassisTempThresholdCrit": {
    "name": "resourceChassisTempThresholdCrit",
    "oid": "1.3.6.1.4.1.10734.3.3.2.5.5.3",
    "nodetype": "scalar",
    "class": "objecttype",
    "syntax": {
      "type": "Integer32",
      "class": "type"
    },
    "maxaccess": "read-only",
    "status": "current",
    "description": "The critical threshold value for chassis temperature."
  },
  "resourceChassisTempRangeMin": {
    "name": "resourceChassisTempRangeMin",
    "oid": "1.3.6.1.4.1.10734.3.3.2.5.5.4",
    "nodetype": "scalar",
    "class": "objecttype",
    "syntax": {
      "type": "Integer32",
      "class": "type"
    },
    "maxaccess": "read-only",
    "status": "current",
    "description": "The minimum value of the chassis temperature range."
  },
  "resourceChassisTempRangeMax": {
    "name": "resourceChassisTempRangeMax",
    "oid": "1.3.6.1.4.1.10734.3.3.2.5.5.5",
    "nodetype": "scalar",
    "class": "objecttype",
    "syntax": {
      "type": "Integer32",
      "class": "type"
    },
    "maxaccess": "read-only",
    "status": "current",
    "description": "The maximum value of the chassis temperature range."
  },
  "resourcePowerSupplyObjs": {
    "name": "resourcePowerSupplyObjs",
    "oid": "1.3.6.1.4.1.10734.3.3.2.5.9",
    "class": "objectidentity",
    "status": "current",
    "description": "Sub-tree of power supply information."
  },
  "resourcePowerSupplyStatus": {
    "name": "resourcePowerSupplyStatus",
    "oid": "1.3.6.1.4.1.10734.3.3.2.5.9.1",
    "nodetype": "scalar",
    "class": "objecttype",
    "syntax": {
      "type": "ResourceState",
      "class": "type"
    },
    "maxaccess": "read-only",
    "status": "deprecated",
    "description": "DEPRECATED as of TOS V. 3.5.0. If the device has dual power supplies and power supply monitoring is enabled, this value indicates whether one or both power supplies is functional (red or green respectively). Otherwise the value is unknown."
  },
  "resourcePowerSupplyQuantity": {
    "name": "resourcePowerSupplyQuantity",
    "oid": "1.3.6.1.4.1.10734.3.3.2.5.9.2",
    "nodetype": "scalar",
    "class": "objecttype",
    "syntax": {
      "type": "Integer32",
      "class": "type"
    },
    "maxaccess": "read-only",
    "status": "current",
    "description": "The number of power supplies (1 or 2)."
  },
  "resourcePowerSupplyMonitoring": {
    "name": "resourcePowerSupplyMonitoring",
    "oid": "1.3.6.1.4.1.10734.3.3.2.5.9.3",
    "nodetype": "scalar",
    "class": "objecttype",
    "syntax": {
      "type": "Integer32",
      "class": "type"
    },
    "maxaccess": "read-only",
    "status": "current",
    "description": "If power supply monitoring is currently enabled, this value is 1; otherwise, this value is 0."
  },
  "resourcePowerSupplyTable": {
    "name": "resourcePowerSupplyTable",
    "oid": "1.3.6.1.4.1.10734.3.3.2.5.9.4",
    "nodetype": "table",
    "class": "objecttype",
    "maxaccess": "not-accessible",
    "status": "current",
    "description": "Table of power supplies on the device. The number of entries depends on the value of resourcePowerSupplyQuantity. The maximum number of entries is implementation dependent."
  },
  "resourcePowerSupplyEntry": {
    "name": "resourcePowerSupplyEntry",
    "oid": "1.3.6.1.4.1.10734.3.3.2.5.9.4.1",
    "nodetype": "row",
    "class": "objecttype",
    "maxaccess": "not-accessible",
    "indices": [
      {
        "module": "TPT-RESOURCE-MIB",
        "object": "powerSupplyUnitIndex",
        "implied": 0
      }
    ],
    "status": "current",
    "description": "An entry in the power supply table. Rows cannot be created or deleted."
  },
  "powerSupplyUnitIndex": {
    "name": "powerSupplyUnitIndex",
    "oid": "1.3.6.1.4.1.10734.3.3.2.5.9.4.1.1",
    "nodetype": "column",
    "class": "objecttype",
    "syntax": {
      "type": "Integer32",
      "class": "type"
    },
    "maxaccess": "read-only",
    "status": "current",
    "description": "Index into the power supply units on a device. Starts with 1"
  },
  "powerSupplyStatus": {
    "name": "powerSupplyStatus",
    "oid": "1.3.6.1.4.1.10734.3.3.2.5.9.4.1.2",
    "nodetype": "column",
    "class": "objecttype",
    "syntax": {
      "type": "ResourceState",
      "class": "type"
    },
    "maxaccess": "read-only",
    "status": "current",
    "description": "If the device has dual power supplies and power supply monitoring is enabled, this value indicates whether one or both power supplies is functional (red or green respectively). Otherwise the value is unknown."
  },
  "resourceLogCountObjs": {
    "name": "resourceLogCountObjs",
    "oid": "1.3.6.1.4.1.10734.3.3.2.5.7",
    "class": "objectidentity",
    "status": "current",
    "description": "Sub-tree of system log entry counts by type."
  },
  "resourceLogCountCritical": {
    "name": "resourceLogCountCritical",
    "oid": "1.3.6.1.4.1.10734.3.3.2.5.7.1",
    "nodetype": "scalar",
    "class": "objecttype",
    "syntax": {
      "type": "Unsigned32",
      "class": "type"
    },
    "maxaccess": "read-only",
    "status": "current",
    "description": "The number of system log entries of type 'critical'."
  },
  "resourceLogCountError": {
    "name": "resourceLogCountError",
    "oid": "1.3.6.1.4.1.10734.3.3.2.5.7.2",
    "nodetype": "scalar",
    "class": "objecttype",
    "syntax": {
      "type": "Unsigned32",
      "class": "type"
    },
    "maxaccess": "read-only",
    "status": "current",
    "description": "The number of system log entries of type 'error'."
  },
  "resourceLogCountWarning": {
    "name": "resourceLogCountWarning",
    "oid": "1.3.6.1.4.1.10734.3.3.2.5.7.3",
    "nodetype": "scalar",
    "class": "objecttype",
    "syntax": {
      "type": "Unsigned32",
      "class": "type"
    },
    "maxaccess": "read-only",
    "status": "current",
    "description": "The number of system log entries of type 'warning'."
  },
  "resourceLogCountInfo": {
    "name": "resourceLogCountInfo",
    "oid": "1.3.6.1.4.1.10734.3.3.2.5.7.4",
    "nodetype": "scalar",
    "class": "objecttype",
    "syntax": {
      "type": "Unsigned32",
      "class": "type"
    },
    "maxaccess": "read-only",
    "status": "current",
    "description": "The number of system log entries of type 'info'."
  },
  "resourceMetricObjs": {
    "name": "resourceMetricObjs",
    "oid": "1.3.6.1.4.1.10734.3.3.2.5.8",
    "class": "objectidentity",
    "status": "current",
    "description": "Sub-tree of selected system performance metrics."
  },
  "resourceMetricFastpath": {
    "name": "resourceMetricFastpath",
    "oid": "1.3.6.1.4.1.10734.3.3.2.5.8.1",
    "nodetype": "scalar",
    "class": "objecttype",
    "syntax": {
      "type": "Counter64",
      "class": "type"
    },
    "maxaccess": "read-only",
    "status": "current",
    "description": "Fast path throughput in bits per second."
  },
  "resourceMetricSmartpath": {
    "name": "resourceMetricSmartpath",
    "oid": "1.3.6.1.4.1.10734.3.3.2.5.8.2",
    "nodetype": "scalar",
    "class": "objecttype",
    "syntax": {
      "type": "Counter64",
      "class": "type"
    },
    "maxaccess": "read-only",
    "status": "current",
    "description": "Smart path throughput in bits per second."
  },
  "resourceMetricCongestion": {
    "name": "resourceMetricCongestion",
    "oid": "1.3.6.1.4.1.10734.3.3.2.5.8.3",
    "nodetype": "scalar",
    "class": "objecttype",
    "syntax": {
      "type": "Counter64",
      "class": "type"
    },
    "maxaccess": "read-only",
    "status": "current",
    "description": "Congestion count in packets."
  },
  "resourceVersion": {
    "name": "resourceVersion",
    "oid": "1.3.6.1.4.1.10734.3.3.2.5.6",
    "nodetype": "scalar",
    "class": "objecttype",
    "syntax": {
      "type": "OCTET STRING",
      "class": "type",
      "constraints": {
        "size": [
          {
            "min": 0,
            "max": 60
          }
        ]
      }
    },
    "maxaccess": "read-only",
    "status": "current",
    "description": "Build version and date."
  },
  "resourceDateTime": {
    "name": "resourceDateTime",
    "oid": "1.3.6.1.4.1.10734.3.3.2.5.10",
    "nodetype": "scalar",
    "class": "objecttype",
    "syntax": {
      "type": "Unsigned32",
      "class": "type"
    },
    "maxaccess": "read-only",
    "status": "current",
    "description": "Current date and time of device in seconds since January 1, 1970. No timezone offset (UTC)"
  },
  "resourceSnmpRunState": {
    "name": "resourceSnmpRunState",
    "oid": "1.3.6.1.4.1.10734.3.3.2.5.11",
    "nodetype": "scalar",
    "class": "objecttype",
    "syntax": {
      "type": "SnmpVersions",
      "class": "type"
    },
    "maxaccess": "read-only",
    "status": "current",
    "description": "An indicator of which SNMP versions are running on the device."
  },
  "resourceSnmpConfig": {
    "name": "resourceSnmpConfig",
    "oid": "1.3.6.1.4.1.10734.3.3.2.5.12",
    "nodetype": "scalar",
    "class": "objecttype",
    "syntax": {
      "type": "SnmpVersions",
      "class": "type"
    },
    "maxaccess": "read-only",
    "status": "current",
    "description": "An indicator of which SNMP versions are configured on the device."
  },
  "resourceRemoteAuthEnabled": {
    "name": "resourceRemoteAuthEnabled",
    "oid": "1.3.6.1.4.1.10734.3.3.2.5.13",
    "nodetype": "scalar",
    "class": "objecttype",
    "syntax": {
      "type": "EnabledOrNot",
      "class": "type"
    },
    "maxaccess": "read-only",
    "status": "current",
    "description": "An indicator of whether remote authentication is enabled on the device."
  },
  "resourceRemoteAuthTimeout": {
    "name": "resourceRemoteAuthTimeout",
    "oid": "1.3.6.1.4.1.10734.3.3.2.5.14",
    "nodetype": "scalar",
    "class": "objecttype",
    "syntax": {
      "type": "Integer32",
      "class": "type"
    },
    "maxaccess": "read-only",
    "status": "current",
    "description": "The configured remote authentication timeout value in seconds."
  },
  "resourceRemoteAuthType": {
    "name": "resourceRemoteAuthType",
    "oid": "1.3.6.1.4.1.10734.3.3.2.5.15",
    "nodetype": "scalar",
    "class": "objecttype",
    "syntax": {
      "type": "RemoteAuthType",
      "class": "type"
    },
    "maxaccess": "read-only",
    "status": "current",
    "description": "An indicator of which remote authentication mechanism is enabled on the device."
  },
  "tptResourceNotifyDeviceID": {
    "name": "tptResourceNotifyDeviceID",
    "oid": "1.3.6.1.4.1.10734.3.3.3.1.61",
    "nodetype": "scalar",
    "class": "objecttype",
    "syntax": {
      "type": "OCTET STRING",
      "class": "type",
      "constraints": {
        "size": [
          {
            "min": 0,
            "max": 40
          }
        ]
      }
    },
    "maxaccess": "read-only",
    "status": "current",
    "description": "The unique identifier of the device sending this notification."
  },
  "tptResourceNotifyIdentifier": {
    "name": "tptResourceNotifyIdentifier",
    "oid": "1.3.6.1.4.1.10734.3.3.3.1.62",
    "nodetype": "scalar",
    "class": "objecttype",
    "syntax": {
      "type": "ResourceIdentifier",
      "class": "type"
    },
    "maxaccess": "read-only",
    "status": "current",
    "description": "The type of the resource that triggered this notification."
  },
  "tptResourceNotifyFSIndex": {
    "name": "tptResourceNotifyFSIndex",
    "oid": "1.3.6.1.4.1.10734.3.3.3.1.63",
    "nodetype": "scalar",
    "class": "objecttype",
    "syntax": {
      "type": "Unsigned32",
      "class": "type"
    },
    "maxaccess": "read-only",
    "status": "current",
    "description": "For a filesystem resource, the index of the filesystem (otherwise 0)."
  },
  "tptResourceNotifyCurrentValue": {
    "name": "tptResourceNotifyCurrentValue",
    "oid": "1.3.6.1.4.1.10734.3.3.3.1.64",
    "nodetype": "scalar",
    "class": "objecttype",
    "syntax": {
      "type": "Integer32",
      "class": "type"
    },
    "maxaccess": "read-only",
    "status": "current",
    "description": "The current value of the resource that triggered this notification."
  },
  "tptResourceNotifyThresholdMaj": {
    "name": "tptResourceNotifyThresholdMaj",
    "oid": "1.3.6.1.4.1.10734.3.3.3.1.65",
    "nodetype": "scalar",
    "class": "objecttype",
    "syntax": {
      "type": "Integer32",
      "class": "type"
    },
    "maxaccess": "read-only",
    "status": "current",
    "description": "The major threshold of this resource (between green and yellow states)."
  },
  "tptResourceNotifyThresholdCrit": {
    "name": "tptResourceNotifyThresholdCrit",
    "oid": "1.3.6.1.4.1.10734.3.3.3.1.66",
    "nodetype": "scalar",
    "class": "objecttype",
    "syntax": {
      "type": "Integer32",
      "class": "type"
    },
    "maxaccess": "read-only",
    "status": "current",
    "description": "The critical threshold of this resource (between yellow and red states)."
  },
  "tptResourceNotifyRangeMin": {
    "name": "tptResourceNotifyRangeMin",
    "oid": "1.3.6.1.4.1.10734.3.3.3.1.67",
    "nodetype": "scalar",
    "class": "objecttype",
    "syntax": {
      "type": "Integer32",
      "class": "type"
    },
    "maxaccess": "read-only",
    "status": "current",
    "description": "The minimum end of the range of values that this resource can take."
  },
  "tptResourceNotifyRangeMax": {
    "name": "tptResourceNotifyRangeMax",
    "oid": "1.3.6.1.4.1.10734.3.3.3.1.68",
    "nodetype": "scalar",
    "class": "objecttype",
    "syntax": {
      "type": "Integer32",
      "class": "type"
    },
    "maxaccess": "read-only",
    "status": "current",
    "description": "The maximum end of the range of values that this resource can take."
  },
  "tptResourceNotifyStateBefore": {
    "name": "tptResourceNotifyStateBefore",
    "oid": "1.3.6.1.4.1.10734.3.3.3.1.69",
    "nodetype": "scalar",
    "class": "objecttype",
    "syntax": {
      "type": "ResourceState",
      "class": "type"
    },
    "maxaccess": "read-only",
    "status": "current",
    "description": "The state of this resource before the current threshold transition."
  },
  "tptResourceNotifyStateAfter": {
    "name": "tptResourceNotifyStateAfter",
    "oid": "1.3.6.1.4.1.10734.3.3.3.1.70",
    "nodetype": "scalar",
    "class": "objecttype",
    "syntax": {
      "type": "ResourceState",
      "class": "type"
    },
    "maxaccess": "read-only",
    "status": "current",
    "description": "The state of this resource after the current threshold transition."
  },
  "tptResourceNotifyTimeStamp": {
    "name": "tptResourceNotifyTimeStamp",
    "oid": "1.3.6.1.4.1.10734.3.3.3.1.71",
    "nodetype": "scalar",
    "class": "objecttype",
    "syntax": {
      "type": "Unsigned32",
      "class": "type"
    },
    "maxaccess": "read-only",
    "status": "current",
    "description": "The time of the threshold crossing represented by this notification (in seconds since January 1, 1970)."
  },
  "tptResourceNotifySubIdentifier": {
    "name": "tptResourceNotifySubIdentifier",
    "oid": "1.3.6.1.4.1.10734.3.3.3.1.72",
    "nodetype": "scalar",
    "class": "objecttype",
    "syntax": {
      "type": "Integer32",
      "class": "type"
    },
    "maxaccess": "read-only",
    "status": "current",
    "description": "Sub-Identifier into the type of the resource which trigger this notification. It starts with 1. It is not used in models 5100N or older (set to 0)."
  },
  "tptResourceNotify": {
    "name": "tptResourceNotify",
    "oid": "1.3.6.1.4.1.10734.3.3.3.0.14",
    "class": "notificationtype",
    "objects": [
      {
        "module": "TPT-RESOURCE-MIB",
        "object": "tptResourceNotifyDeviceID"
      },
      {
        "module": "TPT-RESOURCE-MIB",
        "object": "tptResourceNotifyIdentifier"
      },
      {
        "module": "TPT-RESOURCE-MIB",
        "object": "tptResourceNotifyFSIndex"
      },
      {
        "module": "TPT-RESOURCE-MIB",
        "object": "tptResourceNotifyCurrentValue"
      },
      {
        "module": "TPT-RESOURCE-MIB",
        "object": "tptResourceNotifyThresholdMaj"
      },
      {
        "module": "TPT-RESOURCE-MIB",
        "object": "tptResourceNotifyThresholdCrit"
      },
      {
        "module": "TPT-RESOURCE-MIB",
        "object": "tptResourceNotifyRangeMin"
      },
      {
        "module": "TPT-RESOURCE-MIB",
        "object": "tptResourceNotifyRangeMax"
      },
      {
        "module": "TPT-RESOURCE-MIB",
        "object": "tptResourceNotifyStateBefore"
      },
      {
        "module": "TPT-RESOURCE-MIB",
        "object": "tptResourceNotifyStateAfter"
      },
      {
        "module": "TPT-RESOURCE-MIB",
        "object": "tptResourceNotifyTimeStamp"
      },
      {
        "module": "TPT-RESOURCE-MIB",
        "object": "tptResourceNotifySubIdentifier"
      }
    ],
    "status": "current",
    "description": "Notification: Used to inform the management station that a resource parameter has crossed a predefined threshold."
  },
  "meta": {
    "comments": [
      "ASN.1 source file:///Users/neermitt/kusanagi/mibs.snmplabs.com/asn1/TPT-RESOURCE-MIB",
      "Produced by pysmi-0.3.4 at Fri May 24 22:13:04 2019",
      "On host NEERMITT-M-J0NV platform Darwin version 18.6.0 by user neermitt",
      "Using Python version 3.7.3 (default, Mar 27 2019, 09:23:15) "
    ],
    "module": "TPT-RESOURCE-MIB"
  }
}