{
  "imports": {
    "class": "imports",
    "INET-ADDRESS-MIB": [
      "InetAddressType",
      "InetAddress"
    ],
    "SNMPv2-CONF": [
      "NOTIFICATION-GROUP",
      "MODULE-COMPLIANCE",
      "OBJECT-GROUP"
    ],
    "SNMPv2-SMI": [
      "NOTIFICATION-TYPE",
      "OBJECT-IDENTITY",
      "Integer32",
      "Bits",
      "iso",
      "IpAddress",
      "Counter32",
      "MODULE-IDENTITY",
      "MibIdentifier",
      "OBJECT-TYPE",
      "TimeTicks",
      "Counter64",
      "Gauge32",
      "Unsigned32"
    ],
    "SNMPv2-TC": [
      "MacAddress",
      "DisplayString",
      "TimeStamp",
      "TEXTUAL-CONVENTION"
    ],
    "TRAPEZE-NETWORKS-AP-TC": [
      "TrpzApNum",
      "TrpzRssi",
      "TrpzAccessType",
      "TrpzRadioNum",
      "TrpzRadioRate",
      "TrpzApSerialNum"
    ],
    "TRAPEZE-NETWORKS-BASIC-TC": [
      "TrpzPhysPortNumberOrZero"
    ],
    "TRAPEZE-NETWORKS-CLIENT-SESSION-TC": [
      "TrpzClientSessionState",
      "TrpzClientDeviceGroupName",
      "TrpzClientAccessMode",
      "TrpzClientDeviceType",
      "TrpzClientDeviceProfileName",
      "TrpzUserAccessType",
      "TrpzClientAuthenProtocolType"
    ],
    "TRAPEZE-NETWORKS-ROOT-MIB": [
      "trpzMibs"
    ]
  },
  "trpzClientSessionMib": {
    "name": "trpzClientSessionMib",
    "oid": "1.3.6.1.4.1.14525.4.4",
    "class": "moduleidentity",
    "revisions": [
      {
        "revision": "2012-04-20 01:12",
        "description": "v3.1.2: Added three new columnar objects: trpzClSessClientSessDeviceType, trpzClSessClientSessDeviceGroup, trpzClSessClientSessDeviceProfileName. (for 8.0 release)"
      },
      {
        "revision": "2011-12-06 01:10",
        "description": "v3.1.0: Added a new table: trpzClSessClientAddressTable to hold the clients' Internet addresses. (for 8.0 release)"
      },
      {
        "revision": "2011-05-18 01:00",
        "description": "v3.0.0: Obsoleted a previously deprecated object: 'trpzClSessClientSessAuthMethod' and the associated Textual Convention: 'TrpzAuthMethod'. This will be published in 7.5 release."
      },
      {
        "revision": "2008-10-23 00:56",
        "description": "v2.4.1: Using the new TC TrpzPhysPortNumberOrZero instead of ''Unsigned32 (0..1024)''. This will be published in 7.1 release."
      },
      {
        "revision": "2008-05-23 00:55",
        "description": "v2.4.0: Updated conformance section to reflect the history of changes to this MIB: added more compliance statements and groups. This will be published in 7.0 release."
      },
      {
        "revision": "2007-11-01 00:54",
        "description": "v2.3.4: Added two new columnar objects: - trpzClSessClientSessPhysPortNum, - trpzClSessRoamHistPhysPortNum, to indicate the port used by wired-auth clients. (for 6.2 release)"
      },
      {
        "revision": "2007-10-09 00:51",
        "description": "v2.3.1: Added four new columnar objects: - trpzClSessClientSessAccessMode, obsoleting trpzClSessClientSessAccessType; - trpzClSessClientSessApNum, obsoleting trpzClSessClientSessPortOrNum; - trpzClSessRoamHistAccessMode, obsoleting trpzClSessRoamHistAccessType; - trpzClSessRoamHistApNum, obsoleting trpzClSessRoamHistApNumOrPort. Reason: in 6.0, direct- and network-attached APs were unified. (for 6.2 release)"
      },
      {
        "revision": "2006-11-16 00:43",
        "description": "v2.2.1: added one value (21) to TrpzSessState"
      },
      {
        "revision": "2006-10-17 00:42",
        "description": "v2.2.0: Described semantics of trpzClSessRoamHistTimeStamp"
      },
      {
        "revision": "2006-09-26 00:32",
        "description": "v2.1.1: Added three new columnar objects: - trpzClSessClientSessDot1xAuthMethod, to be used instead of trpzClSessClientSessAuthMethod; - trpzClSessClientSessSessionState, to be used instead of trpzClSessClientSessState; - trpzClSessClientSessLoginType, to provide context for interpreting the values of the above objects (Dot1xAuthMethod, SessionState). Changed behaviour for trpzClSessClientSessAuthServer: provides system IP when auth is done via local DB (it used to be 0.0.0.0 in such cases)."
      },
      {
        "revision": "2006-07-29 00:21",
        "description": "v2.0.2: Fixed imports and compliance group"
      },
      {
        "revision": "2006-06-06 00:10",
        "description": "v2.0.1: Adding scalar for total number of sessions."
      },
      {
        "revision": "2006-03-30 00:08",
        "description": "v1.0: Initial version, for 4.1 release"
      }
    ],
    "lastupdated": "201204200112Z",
    "organization": "Trapeze Networks",
    "contactinfo": "Trapeze Networks Technical Support www.trapezenetworks.com US: 866.TRPZ.TAC International: 925.474.2400 support@trapezenetworks.com",
    "description": "Client Session MIB. AP = Access Point; AC = Access Controller (wireless switch), the device that runs a SNMP Agent implementing this MIB. Copyright 2005-2012 Trapeze Networks, Inc. All rights reserved. This Trapeze Networks SNMP Management Information Base Specification (Specification) embodies Trapeze Networks' confidential and proprietary intellectual property. Trapeze Networks retains all title and ownership in the Specification, including any revisions. This Specification is supplied 'AS IS' and Trapeze Networks makes no warranty, either express or implied, as to the use, operation, condition, or performance of the Specification."
  },
  "TrpzEncryptionType": {
    "name": "TrpzEncryptionType",
    "class": "textualconvention",
    "type": {
      "type": "INTEGER",
      "class": "type",
      "constraints": {
        "enumeration": {
          "none": 1,
          "aesCcm": 2,
          "aesOcb": 3,
          "tkip": 4,
          "wep104": 5,
          "wep40": 6,
          "staticWep": 7
        }
      }
    },
    "status": "current",
    "description": "Encryption types."
  },
  "TrpzAuthMethod": {
    "name": "TrpzAuthMethod",
    "class": "textualconvention",
    "type": {
      "type": "INTEGER",
      "class": "type",
      "constraints": {
        "enumeration": {
          "none": 1,
          "identity": 2,
          "notification": 3,
          "nak": 4,
          "md5": 5,
          "otp": 6,
          "tokenCard": 7,
          "tls": 14,
          "leap": 18,
          "ttls": 22,
          "peap": 26,
          "msChapv2": 27,
          "eapExt": 34,
          "passThru": 255
        }
      }
    },
    "status": "obsolete",
    "description": "Authentication methods. Obsolete, use 'TrpzClientAuthenProtocolType' instead."
  },
  "TrpzSessState": {
    "name": "TrpzSessState",
    "class": "textualconvention",
    "type": {
      "type": "INTEGER",
      "class": "type",
      "constraints": {
        "enumeration": {
          "invalid": 1,
          "initializing": 2,
          "assocReqAndAuth": 3,
          "assocAndAuth": 4,
          "wired": 5,
          "webLoginPh1": 6,
          "webLoginPh1B": 7,
          "webLoginPh1F": 8,
          "webLoginPh2": 9,
          "webPortalLogin": 10,
          "authorizing": 11,
          "authorized": 12,
          "active": 13,
          "activePortal": 14,
          "deassociated": 15,
          "roamingAway": 16,
          "updatedToRoam": 17,
          "roamedAway": 18,
          "killing": 19,
          "free": 20,
          "enforceSoda": 21
        }
      }
    },
    "status": "deprecated",
    "description": "Session states."
  },
  "trpzClientSessionObjects": {
    "name": "trpzClientSessionObjects",
    "oid": "1.3.6.1.4.1.14525.4.4.1",
    "class": "objectidentity"
  },
  "trpzClientSessionDataObjects": {
    "name": "trpzClientSessionDataObjects",
    "oid": "1.3.6.1.4.1.14525.4.4.1.1",
    "class": "objectidentity"
  },
  "trpzClSessClientSessionTable": {
    "name": "trpzClSessClientSessionTable",
    "oid": "1.3.6.1.4.1.14525.4.4.1.1.1",
    "nodetype": "table",
    "class": "objecttype",
    "maxaccess": "not-accessible",
    "status": "current",
    "description": "Client Session Table."
  },
  "trpzClSessClientSessionEntry": {
    "name": "trpzClSessClientSessionEntry",
    "oid": "1.3.6.1.4.1.14525.4.4.1.1.1.1",
    "nodetype": "row",
    "class": "objecttype",
    "maxaccess": "not-accessible",
    "indices": [
      {
        "module": "TRAPEZE-NETWORKS-CLIENT-SESSION-MIB",
        "object": "trpzClSessClientSessMacAddress",
        "implied": 0
      }
    ],
    "status": "current",
    "description": "Information about a particular client session."
  },
  "trpzClSessClientSessMacAddress": {
    "name": "trpzClSessClientSessMacAddress",
    "oid": "1.3.6.1.4.1.14525.4.4.1.1.1.1.1",
    "nodetype": "column",
    "class": "objecttype",
    "syntax": {
      "type": "MacAddress",
      "class": "type"
    },
    "maxaccess": "not-accessible",
    "status": "current",
    "description": "Client MAC address."
  },
  "trpzClSessClientSessSessionId": {
    "name": "trpzClSessClientSessSessionId",
    "oid": "1.3.6.1.4.1.14525.4.4.1.1.1.1.2",
    "nodetype": "column",
    "class": "objecttype",
    "syntax": {
      "type": "DisplayString",
      "class": "type",
      "constraints": {
        "size": [
          {
            "min": 0,
            "max": 30
          }
        ]
      }
    },
    "maxaccess": "read-only",
    "status": "current",
    "description": "Session ID is a string long enough to be sure we can make it unique over a long time."
  },
  "trpzClSessClientSessUsername": {
    "name": "trpzClSessClientSessUsername",
    "oid": "1.3.6.1.4.1.14525.4.4.1.1.1.1.3",
    "nodetype": "column",
    "class": "objecttype",
    "syntax": {
      "type": "DisplayString",
      "class": "type",
      "constraints": {
        "size": [
          {
            "min": 0,
            "max": 80
          }
        ]
      }
    },
    "maxaccess": "read-only",
    "status": "current",
    "description": "Client user name."
  },
  "trpzClSessClientSessIpAddress": {
    "name": "trpzClSessClientSessIpAddress",
    "oid": "1.3.6.1.4.1.14525.4.4.1.1.1.1.4",
    "nodetype": "column",
    "class": "objecttype",
    "syntax": {
      "type": "IpAddress",
      "class": "type"
    },
    "maxaccess": "read-only",
    "status": "current",
    "description": "Client IP address. If the client has no IP address, the value will be 0.0.0.0."
  },
  "trpzClSessClientSessEncryptionType": {
    "name": "trpzClSessClientSessEncryptionType",
    "oid": "1.3.6.1.4.1.14525.4.4.1.1.1.1.5",
    "nodetype": "column",
    "class": "objecttype",
    "syntax": {
      "type": "TrpzEncryptionType",
      "class": "type"
    },
    "maxaccess": "read-only",
    "status": "current",
    "description": "Encryption type."
  },
  "trpzClSessClientSessVlan": {
    "name": "trpzClSessClientSessVlan",
    "oid": "1.3.6.1.4.1.14525.4.4.1.1.1.1.6",
    "nodetype": "column",
    "class": "objecttype",
    "syntax": {
      "type": "DisplayString",
      "class": "type",
      "constraints": {
        "size": [
          {
            "min": 0,
            "max": 80
          }
        ]
      }
    },
    "maxaccess": "read-only",
    "status": "current",
    "description": "The name of the client VLAN."
  },
  "trpzClSessClientSessApSerialNum": {
    "name": "trpzClSessClientSessApSerialNum",
    "oid": "1.3.6.1.4.1.14525.4.4.1.1.1.1.7",
    "nodetype": "column",
    "class": "objecttype",
    "syntax": {
      "type": "TrpzApSerialNum",
      "class": "type"
    },
    "maxaccess": "read-only",
    "status": "current",
    "description": "Serial Number of the AP this client is connected to. It is a zero length string when wired access is used."
  },
  "trpzClSessClientSessRadioNum": {
    "name": "trpzClSessClientSessRadioNum",
    "oid": "1.3.6.1.4.1.14525.4.4.1.1.1.1.8",
    "nodetype": "column",
    "class": "objecttype",
    "syntax": {
      "type": "TrpzRadioNum",
      "class": "type"
    },
    "maxaccess": "read-only",
    "status": "current",
    "description": "Number of the Radio that provides service to this client. It is 'not-applicable' when wired access is used."
  },
  "trpzClSessClientSessAccessType": {
    "name": "trpzClSessClientSessAccessType",
    "oid": "1.3.6.1.4.1.14525.4.4.1.1.1.1.9",
    "nodetype": "column",
    "class": "objecttype",
    "syntax": {
      "type": "TrpzAccessType",
      "class": "type"
    },
    "maxaccess": "read-only",
    "status": "obsolete",
    "description": "Access type this client uses (via AP, DAP or wired). Obsoleted by trpzClSessClientSessAccessMode."
  },
  "trpzClSessClientSessAuthMethod": {
    "name": "trpzClSessClientSessAuthMethod",
    "oid": "1.3.6.1.4.1.14525.4.4.1.1.1.1.10",
    "nodetype": "column",
    "class": "objecttype",
    "syntax": {
      "type": "TrpzAuthMethod",
      "class": "type"
    },
    "maxaccess": "read-only",
    "status": "obsolete",
    "description": "Authentication Method. Obsolete, use trpzClSessClientSessDot1xAuthMethod instead."
  },
  "trpzClSessClientSessAuthServer": {
    "name": "trpzClSessClientSessAuthServer",
    "oid": "1.3.6.1.4.1.14525.4.4.1.1.1.1.11",
    "nodetype": "column",
    "class": "objecttype",
    "syntax": {
      "type": "IpAddress",
      "class": "type"
    },
    "maxaccess": "read-only",
    "status": "current",
    "description": "Authentication Server's IP Address. If the client is authenticated via the local DB, or not authenticated, its value will be the system IP."
  },
  "trpzClSessClientSessPortOrNum": {
    "name": "trpzClSessClientSessPortOrNum",
    "oid": "1.3.6.1.4.1.14525.4.4.1.1.1.1.12",
    "nodetype": "column",
    "class": "objecttype",
    "syntax": {
      "type": "Unsigned32",
      "class": "type"
    },
    "maxaccess": "read-only",
    "status": "obsolete",
    "description": "Port number. Obsoleted by trpzClSessClientSessApNum."
  },
  "trpzClSessClientSessVlanTag": {
    "name": "trpzClSessClientSessVlanTag",
    "oid": "1.3.6.1.4.1.14525.4.4.1.1.1.1.13",
    "nodetype": "column",
    "class": "objecttype",
    "syntax": {
      "type": "Unsigned32",
      "class": "type"
    },
    "maxaccess": "read-only",
    "status": "current",
    "description": "VLAN tag."
  },
  "trpzClSessClientSessTimeStamp": {
    "name": "trpzClSessClientSessTimeStamp",
    "oid": "1.3.6.1.4.1.14525.4.4.1.1.1.1.14",
    "nodetype": "column",
    "class": "objecttype",
    "syntax": {
      "type": "TimeStamp",
      "class": "type"
    },
    "maxaccess": "read-only",
    "status": "current",
    "description": "Session start time stamp."
  },
  "trpzClSessClientSessSsid": {
    "name": "trpzClSessClientSessSsid",
    "oid": "1.3.6.1.4.1.14525.4.4.1.1.1.1.15",
    "nodetype": "column",
    "class": "objecttype",
    "syntax": {
      "type": "DisplayString",
      "class": "type",
      "constraints": {
        "size": [
          {
            "min": 0,
            "max": 33
          }
        ]
      }
    },
    "maxaccess": "read-only",
    "status": "current",
    "description": "SSID."
  },
  "trpzClSessClientSessState": {
    "name": "trpzClSessClientSessState",
    "oid": "1.3.6.1.4.1.14525.4.4.1.1.1.1.16",
    "nodetype": "column",
    "class": "objecttype",
    "syntax": {
      "type": "TrpzSessState",
      "class": "type"
    },
    "maxaccess": "read-only",
    "status": "deprecated",
    "description": "Session state. Deprecated, use trpzClSessClientSessSessionState instead."
  },
  "trpzClSessClientSessLoginType": {
    "name": "trpzClSessClientSessLoginType",
    "oid": "1.3.6.1.4.1.14525.4.4.1.1.1.1.17",
    "nodetype": "column",
    "class": "objecttype",
    "syntax": {
      "type": "TrpzUserAccessType",
      "class": "type"
    },
    "maxaccess": "read-only",
    "status": "current",
    "description": "Login type (mac, web, dot1x or last-resort)."
  },
  "trpzClSessClientSessDot1xAuthMethod": {
    "name": "trpzClSessClientSessDot1xAuthMethod",
    "oid": "1.3.6.1.4.1.14525.4.4.1.1.1.1.18",
    "nodetype": "column",
    "class": "objecttype",
    "syntax": {
      "type": "TrpzClientAuthenProtocolType",
      "class": "type"
    },
    "maxaccess": "read-only",
    "status": "current",
    "description": "Dot1x Authentication Method."
  },
  "trpzClSessClientSessSessionState": {
    "name": "trpzClSessClientSessSessionState",
    "oid": "1.3.6.1.4.1.14525.4.4.1.1.1.1.19",
    "nodetype": "column",
    "class": "objecttype",
    "syntax": {
      "type": "TrpzClientSessionState",
      "class": "type"
    },
    "maxaccess": "read-only",
    "status": "current",
    "description": "Session non-intermediate state."
  },
  "trpzClSessClientSessAccessMode": {
    "name": "trpzClSessClientSessAccessMode",
    "oid": "1.3.6.1.4.1.14525.4.4.1.1.1.1.20",
    "nodetype": "column",
    "class": "objecttype",
    "syntax": {
      "type": "TrpzClientAccessMode",
      "class": "type"
    },
    "maxaccess": "read-only",
    "status": "current",
    "description": "Access mode (type) this client uses (via AP or wired). Obsoletes trpzClSessClientSessAccessType since in 6.0 directly attached APs and DAPs were unified."
  },
  "trpzClSessClientSessApNum": {
    "name": "trpzClSessClientSessApNum",
    "oid": "1.3.6.1.4.1.14525.4.4.1.1.1.1.21",
    "nodetype": "column",
    "class": "objecttype",
    "syntax": {
      "type": "TrpzApNum",
      "class": "type"
    },
    "maxaccess": "read-only",
    "status": "current",
    "description": "The AP providing wireless service to this client is identified by its administratively assigned AP Number, unique on same AC (switch), regardless of how APs are attached to the AC. Meaningful when trpzClSessClientSessAccessMode = 'ap'. Obsoletes trpzClSessClientSessPortOrNum since in 6.0 directly attached APs and DAPs were unified."
  },
  "trpzClSessClientSessPhysPortNum": {
    "name": "trpzClSessClientSessPhysPortNum",
    "oid": "1.3.6.1.4.1.14525.4.4.1.1.1.1.22",
    "nodetype": "column",
    "class": "objecttype",
    "syntax": {
      "type": "TrpzPhysPortNumberOrZero",
      "class": "type"
    },
    "maxaccess": "read-only",
    "status": "current",
    "description": "The physical port used by this wired-auth client is identified by its port number on the AC (switch). Zero means the port is unknown or not applicable (for example, when trpzClSessClientSessAccessMode = 'ap'). Meaningful when trpzClSessClientSessAccessMode = 'wired'."
  },
  "trpzClSessClientSessDeviceType": {
    "name": "trpzClSessClientSessDeviceType",
    "oid": "1.3.6.1.4.1.14525.4.4.1.1.1.1.23",
    "nodetype": "column",
    "class": "objecttype",
    "syntax": {
      "type": "TrpzClientDeviceType",
      "class": "type"
    },
    "maxaccess": "read-only",
    "status": "current",
    "description": "The type of the client device. Is a zero length string if unknown or the device detection feature is disabled."
  },
  "trpzClSessClientSessDeviceGroup": {
    "name": "trpzClSessClientSessDeviceGroup",
    "oid": "1.3.6.1.4.1.14525.4.4.1.1.1.1.24",
    "nodetype": "column",
    "class": "objecttype",
    "syntax": {
      "type": "TrpzClientDeviceGroupName",
      "class": "type"
    },
    "maxaccess": "read-only",
    "status": "current",
    "description": "The group that the detected client device type belongs to. Is a zero length string if the device type is unknown or the device detection feature is disabled."
  },
  "trpzClSessClientSessDeviceProfileName": {
    "name": "trpzClSessClientSessDeviceProfileName",
    "oid": "1.3.6.1.4.1.14525.4.4.1.1.1.1.25",
    "nodetype": "column",
    "class": "objecttype",
    "syntax": {
      "type": "TrpzClientDeviceProfileName",
      "class": "type"
    },
    "maxaccess": "read-only",
    "status": "current",
    "description": "The name of the device profile associated with the detected client device. A device profile is a collection of policies that apply to one or more types of client devices. Is a zero length string in 'detect-only' mode, if not set or if the device detection feature is disabled. In 'detect-only' mode policy enforcement is disabled."
  },
  "trpzClSessRoamingHistoryTable": {
    "name": "trpzClSessRoamingHistoryTable",
    "oid": "1.3.6.1.4.1.14525.4.4.1.1.2",
    "nodetype": "table",
    "class": "objecttype",
    "maxaccess": "not-accessible",
    "status": "current",
    "description": "Roaming History Table. Expansion of Client Session Table."
  },
  "trpzClSessRoamingHistoryEntry": {
    "name": "trpzClSessRoamingHistoryEntry",
    "oid": "1.3.6.1.4.1.14525.4.4.1.1.2.1",
    "nodetype": "row",
    "class": "objecttype",
    "maxaccess": "not-accessible",
    "indices": [
      {
        "module": "TRAPEZE-NETWORKS-CLIENT-SESSION-MIB",
        "object": "trpzClSessRoamHistMacAddress",
        "implied": 0
      },
      {
        "module": "TRAPEZE-NETWORKS-CLIENT-SESSION-MIB",
        "object": "trpzClSessRoamHistIndex",
        "implied": 0
      }
    ],
    "status": "current",
    "description": "Roaming History Entry."
  },
  "trpzClSessRoamHistMacAddress": {
    "name": "trpzClSessRoamHistMacAddress",
    "oid": "1.3.6.1.4.1.14525.4.4.1.1.2.1.1",
    "nodetype": "column",
    "class": "objecttype",
    "syntax": {
      "type": "MacAddress",
      "class": "type"
    },
    "maxaccess": "not-accessible",
    "status": "current",
    "description": "Client MAC address."
  },
  "trpzClSessRoamHistIndex": {
    "name": "trpzClSessRoamHistIndex",
    "oid": "1.3.6.1.4.1.14525.4.4.1.1.2.1.2",
    "nodetype": "column",
    "class": "objecttype",
    "syntax": {
      "type": "Unsigned32",
      "class": "type"
    },
    "maxaccess": "not-accessible",
    "status": "current",
    "description": "Entry index."
  },
  "trpzClSessRoamHistApSerialNum": {
    "name": "trpzClSessRoamHistApSerialNum",
    "oid": "1.3.6.1.4.1.14525.4.4.1.1.2.1.3",
    "nodetype": "column",
    "class": "objecttype",
    "syntax": {
      "type": "TrpzApSerialNum",
      "class": "type"
    },
    "maxaccess": "read-only",
    "status": "current",
    "description": "Serial Number of the AP this client was connected to."
  },
  "trpzClSessRoamHistRadioNum": {
    "name": "trpzClSessRoamHistRadioNum",
    "oid": "1.3.6.1.4.1.14525.4.4.1.1.2.1.4",
    "nodetype": "column",
    "class": "objecttype",
    "syntax": {
      "type": "TrpzRadioNum",
      "class": "type"
    },
    "maxaccess": "read-only",
    "status": "current",
    "description": "Number of the Radio that provided service to this client."
  },
  "trpzClSessRoamHistAccessType": {
    "name": "trpzClSessRoamHistAccessType",
    "oid": "1.3.6.1.4.1.14525.4.4.1.1.2.1.5",
    "nodetype": "column",
    "class": "objecttype",
    "syntax": {
      "type": "TrpzAccessType",
      "class": "type"
    },
    "maxaccess": "read-only",
    "status": "obsolete",
    "description": "Access type used by this client (via AP, DAP or wired). Obsoleted by trpzClSessRoamHistAccessMode."
  },
  "trpzClSessRoamHistApNumOrPort": {
    "name": "trpzClSessRoamHistApNumOrPort",
    "oid": "1.3.6.1.4.1.14525.4.4.1.1.2.1.6",
    "nodetype": "column",
    "class": "objecttype",
    "syntax": {
      "type": "Unsigned32",
      "class": "type"
    },
    "maxaccess": "read-only",
    "status": "obsolete",
    "description": "AP port number, DAP number, or Port number for wired access. Obsoleted by trpzClSessRoamHistApNum."
  },
  "trpzClSessRoamHistIpAddress": {
    "name": "trpzClSessRoamHistIpAddress",
    "oid": "1.3.6.1.4.1.14525.4.4.1.1.2.1.7",
    "nodetype": "column",
    "class": "objecttype",
    "syntax": {
      "type": "IpAddress",
      "class": "type"
    },
    "maxaccess": "read-only",
    "status": "current",
    "description": "IP address of the AC (wireless switch) the client or AP was connected to."
  },
  "trpzClSessRoamHistTimeStamp": {
    "name": "trpzClSessRoamHistTimeStamp",
    "oid": "1.3.6.1.4.1.14525.4.4.1.1.2.1.8",
    "nodetype": "column",
    "class": "objecttype",
    "syntax": {
      "type": "TimeStamp",
      "class": "type"
    },
    "maxaccess": "read-only",
    "status": "current",
    "description": "The difference between the time the session was created on the roamed-to switch and the time the last switch, the one where the user is at currently, started. The timestamp unit is in hundredths of seconds."
  },
  "trpzClSessRoamHistAccessMode": {
    "name": "trpzClSessRoamHistAccessMode",
    "oid": "1.3.6.1.4.1.14525.4.4.1.1.2.1.9",
    "nodetype": "column",
    "class": "objecttype",
    "syntax": {
      "type": "TrpzClientAccessMode",
      "class": "type"
    },
    "maxaccess": "read-only",
    "status": "current",
    "description": "Access mode (type) used by this client (via AP or wired). Obsoletes trpzClSessRoamHistAccessType since in 6.0 directly attached APs and DAPs were unified."
  },
  "trpzClSessRoamHistApNum": {
    "name": "trpzClSessRoamHistApNum",
    "oid": "1.3.6.1.4.1.14525.4.4.1.1.2.1.10",
    "nodetype": "column",
    "class": "objecttype",
    "syntax": {
      "type": "TrpzApNum",
      "class": "type"
    },
    "maxaccess": "read-only",
    "status": "current",
    "description": "The administratively assigned AP Number, unique on same AC (switch), regardless of how APs are attached to the AC. Obsoletes trpzClSessRoamHistApNumOrPort since in 6.0 directly attached APs and DAPs were unified."
  },
  "trpzClSessRoamHistPhysPortNum": {
    "name": "trpzClSessRoamHistPhysPortNum",
    "oid": "1.3.6.1.4.1.14525.4.4.1.1.2.1.11",
    "nodetype": "column",
    "class": "objecttype",
    "syntax": {
      "type": "TrpzPhysPortNumberOrZero",
      "class": "type"
    },
    "maxaccess": "read-only",
    "status": "current",
    "description": "The physical port used by this wired-auth client is identified by its port number on the AC (switch). Zero means the port is unknown or not applicable (for example, when trpzClSessRoamHistAccessMode = 'ap'). Meaningful when trpzClSessRoamHistAccessMode = 'wired'."
  },
  "trpzClSessClientSessionStatisticsTable": {
    "name": "trpzClSessClientSessionStatisticsTable",
    "oid": "1.3.6.1.4.1.14525.4.4.1.1.3",
    "nodetype": "table",
    "class": "objecttype",
    "maxaccess": "not-accessible",
    "status": "current",
    "description": "Client Session Statistics Table."
  },
  "trpzClSessClientSessionStatisticsEntry": {
    "name": "trpzClSessClientSessionStatisticsEntry",
    "oid": "1.3.6.1.4.1.14525.4.4.1.1.3.1",
    "nodetype": "row",
    "class": "objecttype",
    "maxaccess": "not-accessible",
    "indices": [
      {
        "module": "TRAPEZE-NETWORKS-CLIENT-SESSION-MIB",
        "object": "trpzClSessClientSessStatsMacAddress",
        "implied": 0
      }
    ],
    "status": "current",
    "description": "Client Session Statistics Table Entry."
  },
  "trpzClSessClientSessStatsMacAddress": {
    "name": "trpzClSessClientSessStatsMacAddress",
    "oid": "1.3.6.1.4.1.14525.4.4.1.1.3.1.1",
    "nodetype": "column",
    "class": "objecttype",
    "syntax": {
      "type": "MacAddress",
      "class": "type"
    },
    "maxaccess": "not-accessible",
    "status": "current",
    "description": "Client MAC address."
  },
  "trpzClSessClientSessStatsUniPktIn": {
    "name": "trpzClSessClientSessStatsUniPktIn",
    "oid": "1.3.6.1.4.1.14525.4.4.1.1.3.1.2",
    "nodetype": "column",
    "class": "objecttype",
    "syntax": {
      "type": "Counter64",
      "class": "type"
    },
    "maxaccess": "read-only",
    "status": "current",
    "description": "Unicast packets in."
  },
  "trpzClSessClientSessStatsUniOctetIn": {
    "name": "trpzClSessClientSessStatsUniOctetIn",
    "oid": "1.3.6.1.4.1.14525.4.4.1.1.3.1.3",
    "nodetype": "column",
    "class": "objecttype",
    "syntax": {
      "type": "Counter64",
      "class": "type"
    },
    "maxaccess": "read-only",
    "status": "current",
    "description": "Unicast octets in."
  },
  "trpzClSessClientSessStatsUniPktOut": {
    "name": "trpzClSessClientSessStatsUniPktOut",
    "oid": "1.3.6.1.4.1.14525.4.4.1.1.3.1.4",
    "nodetype": "column",
    "class": "objecttype",
    "syntax": {
      "type": "Counter64",
      "class": "type"
    },
    "maxaccess": "read-only",
    "status": "current",
    "description": "Unicast packets out."
  },
  "trpzClSessClientSessStatsUniOctetOut": {
    "name": "trpzClSessClientSessStatsUniOctetOut",
    "oid": "1.3.6.1.4.1.14525.4.4.1.1.3.1.5",
    "nodetype": "column",
    "class": "objecttype",
    "syntax": {
      "type": "Counter64",
      "class": "type"
    },
    "maxaccess": "read-only",
    "status": "current",
    "description": "Unicast octets out."
  },
  "trpzClSessClientSessStatsMultiPktIn": {
    "name": "trpzClSessClientSessStatsMultiPktIn",
    "oid": "1.3.6.1.4.1.14525.4.4.1.1.3.1.6",
    "nodetype": "column",
    "class": "objecttype",
    "syntax": {
      "type": "Counter64",
      "class": "type"
    },
    "maxaccess": "read-only",
    "status": "current",
    "description": "Multicast packets in."
  },
  "trpzClSessClientSessStatsMultiOctetIn": {
    "name": "trpzClSessClientSessStatsMultiOctetIn",
    "oid": "1.3.6.1.4.1.14525.4.4.1.1.3.1.7",
    "nodetype": "column",
    "class": "objecttype",
    "syntax": {
      "type": "Counter64",
      "class": "type"
    },
    "maxaccess": "read-only",
    "status": "current",
    "description": "Multicast octets in."
  },
  "trpzClSessClientSessStatsEncErrPkt": {
    "name": "trpzClSessClientSessStatsEncErrPkt",
    "oid": "1.3.6.1.4.1.14525.4.4.1.1.3.1.8",
    "nodetype": "column",
    "class": "objecttype",
    "syntax": {
      "type": "Counter64",
      "class": "type"
    },
    "maxaccess": "read-only",
    "status": "current",
    "description": "Number of packets with encryption errors."
  },
  "trpzClSessClientSessStatsEncErrOctet": {
    "name": "trpzClSessClientSessStatsEncErrOctet",
    "oid": "1.3.6.1.4.1.14525.4.4.1.1.3.1.9",
    "nodetype": "column",
    "class": "objecttype",
    "syntax": {
      "type": "Counter64",
      "class": "type"
    },
    "maxaccess": "read-only",
    "status": "current",
    "description": "Number of octets with encryption errors."
  },
  "trpzClSessClientSessStatsLastRate": {
    "name": "trpzClSessClientSessStatsLastRate",
    "oid": "1.3.6.1.4.1.14525.4.4.1.1.3.1.10",
    "nodetype": "column",
    "class": "objecttype",
    "syntax": {
      "type": "TrpzRadioRate",
      "class": "type"
    },
    "maxaccess": "read-only",
    "status": "current",
    "description": "Last packet data rate."
  },
  "trpzClSessClientSessStatsLastRssi": {
    "name": "trpzClSessClientSessStatsLastRssi",
    "oid": "1.3.6.1.4.1.14525.4.4.1.1.3.1.11",
    "nodetype": "column",
    "class": "objecttype",
    "syntax": {
      "type": "TrpzRssi",
      "class": "type"
    },
    "maxaccess": "read-only",
    "status": "current",
    "description": "RSSI (Received Signal Strength Indicator) for last packet, in decibels referred to 1 milliwatt (dBm). A higher value indicates a stronger signal."
  },
  "trpzClSessClientSessStatsLastSNR": {
    "name": "trpzClSessClientSessStatsLastSNR",
    "oid": "1.3.6.1.4.1.14525.4.4.1.1.3.1.12",
    "nodetype": "column",
    "class": "objecttype",
    "syntax": {
      "type": "Integer32",
      "class": "type"
    },
    "maxaccess": "read-only",
    "status": "current",
    "description": "Last packet data Signal to Noise Ratio."
  },
  "trpzClSessClientAddressTable": {
    "name": "trpzClSessClientAddressTable",
    "oid": "1.3.6.1.4.1.14525.4.4.1.1.5",
    "nodetype": "table",
    "class": "objecttype",
    "maxaccess": "not-accessible",
    "status": "current",
    "description": "Client Address Table. This table contains the clients' Internet addresses. Each client may have one IPv4 address, one IPv6 link-local address and multiple IPv6 global addresses. Expansion of the Client Session Table."
  },
  "trpzClSessClientAddressEntry": {
    "name": "trpzClSessClientAddressEntry",
    "oid": "1.3.6.1.4.1.14525.4.4.1.1.5.1",
    "nodetype": "row",
    "class": "objecttype",
    "maxaccess": "not-accessible",
    "indices": [
      {
        "module": "TRAPEZE-NETWORKS-CLIENT-SESSION-MIB",
        "object": "trpzClSessClientSessMacAddress",
        "implied": 0
      },
      {
        "module": "TRAPEZE-NETWORKS-CLIENT-SESSION-MIB",
        "object": "trpzClSessClientAddressIndex",
        "implied": 0
      }
    ],
    "status": "current",
    "description": "An entry in the Client Address table. A client's MAC address together with an unsigned integer uniquely identify one of that client's Internet addresses."
  },
  "trpzClSessClientAddressIndex": {
    "name": "trpzClSessClientAddressIndex",
    "oid": "1.3.6.1.4.1.14525.4.4.1.1.5.1.1",
    "nodetype": "column",
    "class": "objecttype",
    "syntax": {
      "type": "Unsigned32",
      "class": "type"
    },
    "maxaccess": "not-accessible",
    "status": "current",
    "description": "Last part of the composite index of the Client Address table. The client is identified by the first part of the composite index: 'trpzClSessClientSessMacAddress'. Index 1 corresponds to the IPv4 address of the client. Index 2 corresponds to the IPv6 link-local address of the client. Indexes 3-9 are reserved for future use. Indexes starting at 10 correspond to IPv6 global addresses of the client; the number of IPv6 addresses per client may vary."
  },
  "trpzClSessClientAddressType": {
    "name": "trpzClSessClientAddressType",
    "oid": "1.3.6.1.4.1.14525.4.4.1.1.5.1.2",
    "nodetype": "column",
    "class": "objecttype",
    "syntax": {
      "type": "InetAddressType",
      "class": "type"
    },
    "maxaccess": "read-only",
    "status": "current",
    "description": "The address type of 'trpzClSessClientAddressValue'."
  },
  "trpzClSessClientAddressValue": {
    "name": "trpzClSessClientAddressValue",
    "oid": "1.3.6.1.4.1.14525.4.4.1.1.5.1.3",
    "nodetype": "column",
    "class": "objecttype",
    "syntax": {
      "type": "InetAddress",
      "class": "type"
    },
    "maxaccess": "read-only",
    "status": "current",
    "description": "Client Internet address. The type of this address is specified in 'trpzClSessClientAddressType'."
  },
  "trpzClSessTotalSessions": {
    "name": "trpzClSessTotalSessions",
    "oid": "1.3.6.1.4.1.14525.4.4.1.1.4",
    "nodetype": "scalar",
    "class": "objecttype",
    "syntax": {
      "type": "Unsigned32",
      "class": "type"
    },
    "maxaccess": "read-only",
    "status": "current",
    "description": "Total number of sessions."
  },
  "trpzClientSessionConformance": {
    "name": "trpzClientSessionConformance",
    "oid": "1.3.6.1.4.1.14525.4.4.1.2",
    "class": "objectidentity"
  },
  "trpzClientSessionCompliances": {
    "name": "trpzClientSessionCompliances",
    "oid": "1.3.6.1.4.1.14525.4.4.1.2.1",
    "class": "objectidentity"
  },
  "trpzClientSessionGroups": {
    "name": "trpzClientSessionGroups",
    "oid": "1.3.6.1.4.1.14525.4.4.1.2.2",
    "class": "objectidentity"
  },
  "trpzClientSessionCompliance": {
    "name": "trpzClientSessionCompliance",
    "oid": "1.3.6.1.4.1.14525.4.4.1.2.1.1",
    "class": "modulecompliance",
    "modulecompliance": [
      {
        "object": "trpzClientSessionCommonGroup",
        "module": "TRAPEZE-NETWORKS-CLIENT-SESSION-MIB"
      }
    ],
    "status": "obsolete",
    "description": "The compliance statement for devices that implement the Client Session MIB. This compliance statement was for releases 4.1 and 4.2 of AC (wireless switch) software. This compliance statement is replaced by trpzClientSessionComplianceRev2."
  },
  "trpzClientSessionComplianceRev2": {
    "name": "trpzClientSessionComplianceRev2",
    "oid": "1.3.6.1.4.1.14525.4.4.1.2.1.2",
    "class": "modulecompliance",
    "modulecompliance": [
      {
        "object": "trpzClientSessScalarsGroup",
        "module": "TRAPEZE-NETWORKS-CLIENT-SESSION-MIB"
      },
      {
        "object": "trpzClientSessClientSessionTableGroup",
        "module": "TRAPEZE-NETWORKS-CLIENT-SESSION-MIB"
      },
      {
        "object": "trpzClientSessRoamingHistoryTableGroup",
        "module": "TRAPEZE-NETWORKS-CLIENT-SESSION-MIB"
      },
      {
        "object": "trpzClientSessClientSessionStatisticsTableGroup",
        "module": "TRAPEZE-NETWORKS-CLIENT-SESSION-MIB"
      }
    ],
    "status": "obsolete",
    "description": "The compliance statement for devices that implement the Client Session MIB. This compliance statement was for releases 5.0 and 6.0 of AC (wireless switch) software. This compliance statement is replaced by trpzClientSessionComplianceRev3."
  },
  "trpzClientSessionComplianceRev3": {
    "name": "trpzClientSessionComplianceRev3",
    "oid": "1.3.6.1.4.1.14525.4.4.1.2.1.3",
    "class": "modulecompliance",
    "modulecompliance": [
      {
        "object": "trpzClientSessScalarsGroup",
        "module": "TRAPEZE-NETWORKS-CLIENT-SESSION-MIB"
      },
      {
        "object": "trpzClientSessClientSessionTableGroupRev2",
        "module": "TRAPEZE-NETWORKS-CLIENT-SESSION-MIB"
      },
      {
        "object": "trpzClientSessRoamingHistoryTableGroupRev2",
        "module": "TRAPEZE-NETWORKS-CLIENT-SESSION-MIB"
      },
      {
        "object": "trpzClientSessClientSessionStatisticsTableGroup",
        "module": "TRAPEZE-NETWORKS-CLIENT-SESSION-MIB"
      }
    ],
    "status": "obsolete",
    "description": "The compliance statement for devices that implement the Client Session MIB. This compliance statement is for releases 6.2 to 7.7 of AC (wireless switch) software. This compliance statement is replaced by trpzClientSessionComplianceRev4."
  },
  "trpzClientSessionComplianceRev4": {
    "name": "trpzClientSessionComplianceRev4",
    "oid": "1.3.6.1.4.1.14525.4.4.1.2.1.4",
    "class": "modulecompliance",
    "modulecompliance": [
      {
        "object": "trpzClientSessScalarsGroup",
        "module": "TRAPEZE-NETWORKS-CLIENT-SESSION-MIB"
      },
      {
        "object": "trpzClientSessClientSessionTableGroupRev3",
        "module": "TRAPEZE-NETWORKS-CLIENT-SESSION-MIB"
      },
      {
        "object": "trpzClientSessRoamingHistoryTableGroupRev2",
        "module": "TRAPEZE-NETWORKS-CLIENT-SESSION-MIB"
      },
      {
        "object": "trpzClSessClientAddressTableGroup",
        "module": "TRAPEZE-NETWORKS-CLIENT-SESSION-MIB"
      },
      {
        "object": "trpzClientSessClientSessionStatisticsTableGroup",
        "module": "TRAPEZE-NETWORKS-CLIENT-SESSION-MIB"
      }
    ],
    "status": "current",
    "description": "The compliance statement for devices that implement the Client Session MIB. This compliance statement is for releases 8.0 and greater of AC (wireless switch) software."
  },
  "trpzClientSessionCommonGroup": {
    "name": "trpzClientSessionCommonGroup",
    "oid": "1.3.6.1.4.1.14525.4.4.1.2.2.1",
    "class": "objectgroup",
    "objects": [
      {
        "module": "TRAPEZE-NETWORKS-CLIENT-SESSION-MIB",
        "object": "trpzClSessClientSessSessionId"
      },
      {
        "module": "TRAPEZE-NETWORKS-CLIENT-SESSION-MIB",
        "object": "trpzClSessClientSessUsername"
      },
      {
        "module": "TRAPEZE-NETWORKS-CLIENT-SESSION-MIB",
        "object": "trpzClSessClientSessIpAddress"
      },
      {
        "module": "TRAPEZE-NETWORKS-CLIENT-SESSION-MIB",
        "object": "trpzClSessClientSessEncryptionType"
      },
      {
        "module": "TRAPEZE-NETWORKS-CLIENT-SESSION-MIB",
        "object": "trpzClSessClientSessVlan"
      },
      {
        "module": "TRAPEZE-NETWORKS-CLIENT-SESSION-MIB",
        "object": "trpzClSessClientSessApSerialNum"
      },
      {
        "module": "TRAPEZE-NETWORKS-CLIENT-SESSION-MIB",
        "object": "trpzClSessClientSessRadioNum"
      },
      {
        "module": "TRAPEZE-NETWORKS-CLIENT-SESSION-MIB",
        "object": "trpzClSessClientSessAccessType"
      },
      {
        "module": "TRAPEZE-NETWORKS-CLIENT-SESSION-MIB",
        "object": "trpzClSessClientSessAuthMethod"
      },
      {
        "module": "TRAPEZE-NETWORKS-CLIENT-SESSION-MIB",
        "object": "trpzClSessClientSessAuthServer"
      },
      {
        "module": "TRAPEZE-NETWORKS-CLIENT-SESSION-MIB",
        "object": "trpzClSessClientSessPortOrNum"
      },
      {
        "module": "TRAPEZE-NETWORKS-CLIENT-SESSION-MIB",
        "object": "trpzClSessClientSessVlanTag"
      },
      {
        "module": "TRAPEZE-NETWORKS-CLIENT-SESSION-MIB",
        "object": "trpzClSessClientSessTimeStamp"
      },
      {
        "module": "TRAPEZE-NETWORKS-CLIENT-SESSION-MIB",
        "object": "trpzClSessClientSessSsid"
      },
      {
        "module": "TRAPEZE-NETWORKS-CLIENT-SESSION-MIB",
        "object": "trpzClSessClientSessState"
      },
      {
        "module": "TRAPEZE-NETWORKS-CLIENT-SESSION-MIB",
        "object": "trpzClSessRoamHistApSerialNum"
      },
      {
        "module": "TRAPEZE-NETWORKS-CLIENT-SESSION-MIB",
        "object": "trpzClSessRoamHistRadioNum"
      },
      {
        "module": "TRAPEZE-NETWORKS-CLIENT-SESSION-MIB",
        "object": "trpzClSessRoamHistAccessType"
      },
      {
        "module": "TRAPEZE-NETWORKS-CLIENT-SESSION-MIB",
        "object": "trpzClSessRoamHistApNumOrPort"
      },
      {
        "module": "TRAPEZE-NETWORKS-CLIENT-SESSION-MIB",
        "object": "trpzClSessRoamHistIpAddress"
      },
      {
        "module": "TRAPEZE-NETWORKS-CLIENT-SESSION-MIB",
        "object": "trpzClSessRoamHistTimeStamp"
      },
      {
        "module": "TRAPEZE-NETWORKS-CLIENT-SESSION-MIB",
        "object": "trpzClSessClientSessStatsUniPktIn"
      },
      {
        "module": "TRAPEZE-NETWORKS-CLIENT-SESSION-MIB",
        "object": "trpzClSessClientSessStatsUniOctetIn"
      },
      {
        "module": "TRAPEZE-NETWORKS-CLIENT-SESSION-MIB",
        "object": "trpzClSessClientSessStatsUniPktOut"
      },
      {
        "module": "TRAPEZE-NETWORKS-CLIENT-SESSION-MIB",
        "object": "trpzClSessClientSessStatsUniOctetOut"
      },
      {
        "module": "TRAPEZE-NETWORKS-CLIENT-SESSION-MIB",
        "object": "trpzClSessClientSessStatsMultiPktIn"
      },
      {
        "module": "TRAPEZE-NETWORKS-CLIENT-SESSION-MIB",
        "object": "trpzClSessClientSessStatsMultiOctetIn"
      },
      {
        "module": "TRAPEZE-NETWORKS-CLIENT-SESSION-MIB",
        "object": "trpzClSessClientSessStatsEncErrPkt"
      },
      {
        "module": "TRAPEZE-NETWORKS-CLIENT-SESSION-MIB",
        "object": "trpzClSessClientSessStatsEncErrOctet"
      },
      {
        "module": "TRAPEZE-NETWORKS-CLIENT-SESSION-MIB",
        "object": "trpzClSessClientSessStatsLastRate"
      },
      {
        "module": "TRAPEZE-NETWORKS-CLIENT-SESSION-MIB",
        "object": "trpzClSessClientSessStatsLastRssi"
      },
      {
        "module": "TRAPEZE-NETWORKS-CLIENT-SESSION-MIB",
        "object": "trpzClSessClientSessStatsLastSNR"
      }
    ],
    "status": "obsolete",
    "description": "Mandatory group of objects implemented to provide Client Session info in releases 4.1 and 4.2 of AC (wireless switch) software. Replaced by trpzClientSessClientSessionTableGroup, trpzClientSessRoamingHistoryTableGroup, trpzClientSessClientSessionStatisticsTableGroup."
  },
  "trpzClientSessScalarsGroup": {
    "name": "trpzClientSessScalarsGroup",
    "oid": "1.3.6.1.4.1.14525.4.4.1.2.2.2",
    "class": "objectgroup",
    "objects": [
      {
        "module": "TRAPEZE-NETWORKS-CLIENT-SESSION-MIB",
        "object": "trpzClSessTotalSessions"
      }
    ],
    "status": "current",
    "description": "Group of scalar objects implemented to provide general Client info in releases 5.0 and greater."
  },
  "trpzClientSessClientSessionTableGroup": {
    "name": "trpzClientSessClientSessionTableGroup",
    "oid": "1.3.6.1.4.1.14525.4.4.1.2.2.3",
    "class": "objectgroup",
    "objects": [
      {
        "module": "TRAPEZE-NETWORKS-CLIENT-SESSION-MIB",
        "object": "trpzClSessClientSessSessionId"
      },
      {
        "module": "TRAPEZE-NETWORKS-CLIENT-SESSION-MIB",
        "object": "trpzClSessClientSessUsername"
      },
      {
        "module": "TRAPEZE-NETWORKS-CLIENT-SESSION-MIB",
        "object": "trpzClSessClientSessIpAddress"
      },
      {
        "module": "TRAPEZE-NETWORKS-CLIENT-SESSION-MIB",
        "object": "trpzClSessClientSessEncryptionType"
      },
      {
        "module": "TRAPEZE-NETWORKS-CLIENT-SESSION-MIB",
        "object": "trpzClSessClientSessVlan"
      },
      {
        "module": "TRAPEZE-NETWORKS-CLIENT-SESSION-MIB",
        "object": "trpzClSessClientSessApSerialNum"
      },
      {
        "module": "TRAPEZE-NETWORKS-CLIENT-SESSION-MIB",
        "object": "trpzClSessClientSessRadioNum"
      },
      {
        "module": "TRAPEZE-NETWORKS-CLIENT-SESSION-MIB",
        "object": "trpzClSessClientSessAccessType"
      },
      {
        "module": "TRAPEZE-NETWORKS-CLIENT-SESSION-MIB",
        "object": "trpzClSessClientSessAuthServer"
      },
      {
        "module": "TRAPEZE-NETWORKS-CLIENT-SESSION-MIB",
        "object": "trpzClSessClientSessPortOrNum"
      },
      {
        "module": "TRAPEZE-NETWORKS-CLIENT-SESSION-MIB",
        "object": "trpzClSessClientSessVlanTag"
      },
      {
        "module": "TRAPEZE-NETWORKS-CLIENT-SESSION-MIB",
        "object": "trpzClSessClientSessTimeStamp"
      },
      {
        "module": "TRAPEZE-NETWORKS-CLIENT-SESSION-MIB",
        "object": "trpzClSessClientSessSsid"
      },
      {
        "module": "TRAPEZE-NETWORKS-CLIENT-SESSION-MIB",
        "object": "trpzClSessClientSessLoginType"
      },
      {
        "module": "TRAPEZE-NETWORKS-CLIENT-SESSION-MIB",
        "object": "trpzClSessClientSessDot1xAuthMethod"
      },
      {
        "module": "TRAPEZE-NETWORKS-CLIENT-SESSION-MIB",
        "object": "trpzClSessClientSessSessionState"
      }
    ],
    "status": "obsolete",
    "description": "Group of columnar objects implemented to provide Client Session info in releases 5.0 and 6.0. Replaced by trpzClientSessClientSessionTableGroupRev2."
  },
  "trpzClientSessRoamingHistoryTableGroup": {
    "name": "trpzClientSessRoamingHistoryTableGroup",
    "oid": "1.3.6.1.4.1.14525.4.4.1.2.2.4",
    "class": "objectgroup",
    "objects": [
      {
        "module": "TRAPEZE-NETWORKS-CLIENT-SESSION-MIB",
        "object": "trpzClSessRoamHistApSerialNum"
      },
      {
        "module": "TRAPEZE-NETWORKS-CLIENT-SESSION-MIB",
        "object": "trpzClSessRoamHistRadioNum"
      },
      {
        "module": "TRAPEZE-NETWORKS-CLIENT-SESSION-MIB",
        "object": "trpzClSessRoamHistAccessType"
      },
      {
        "module": "TRAPEZE-NETWORKS-CLIENT-SESSION-MIB",
        "object": "trpzClSessRoamHistApNumOrPort"
      },
      {
        "module": "TRAPEZE-NETWORKS-CLIENT-SESSION-MIB",
        "object": "trpzClSessRoamHistIpAddress"
      },
      {
        "module": "TRAPEZE-NETWORKS-CLIENT-SESSION-MIB",
        "object": "trpzClSessRoamHistTimeStamp"
      }
    ],
    "status": "obsolete",
    "description": "Group of columnar objects implemented to provide roaming history per Client Session in releases 5.0 and 6.0. Replaced by trpzClientSessRoamingHistoryTableGroupRev2."
  },
  "trpzClientSessClientSessionStatisticsTableGroup": {
    "name": "trpzClientSessClientSessionStatisticsTableGroup",
    "oid": "1.3.6.1.4.1.14525.4.4.1.2.2.5",
    "class": "objectgroup",
    "objects": [
      {
        "module": "TRAPEZE-NETWORKS-CLIENT-SESSION-MIB",
        "object": "trpzClSessClientSessStatsUniPktIn"
      },
      {
        "module": "TRAPEZE-NETWORKS-CLIENT-SESSION-MIB",
        "object": "trpzClSessClientSessStatsUniOctetIn"
      },
      {
        "module": "TRAPEZE-NETWORKS-CLIENT-SESSION-MIB",
        "object": "trpzClSessClientSessStatsUniPktOut"
      },
      {
        "module": "TRAPEZE-NETWORKS-CLIENT-SESSION-MIB",
        "object": "trpzClSessClientSessStatsUniOctetOut"
      },
      {
        "module": "TRAPEZE-NETWORKS-CLIENT-SESSION-MIB",
        "object": "trpzClSessClientSessStatsMultiPktIn"
      },
      {
        "module": "TRAPEZE-NETWORKS-CLIENT-SESSION-MIB",
        "object": "trpzClSessClientSessStatsMultiOctetIn"
      },
      {
        "module": "TRAPEZE-NETWORKS-CLIENT-SESSION-MIB",
        "object": "trpzClSessClientSessStatsEncErrPkt"
      },
      {
        "module": "TRAPEZE-NETWORKS-CLIENT-SESSION-MIB",
        "object": "trpzClSessClientSessStatsEncErrOctet"
      },
      {
        "module": "TRAPEZE-NETWORKS-CLIENT-SESSION-MIB",
        "object": "trpzClSessClientSessStatsLastRate"
      },
      {
        "module": "TRAPEZE-NETWORKS-CLIENT-SESSION-MIB",
        "object": "trpzClSessClientSessStatsLastRssi"
      },
      {
        "module": "TRAPEZE-NETWORKS-CLIENT-SESSION-MIB",
        "object": "trpzClSessClientSessStatsLastSNR"
      }
    ],
    "status": "current",
    "description": "Group of columnar objects implemented to provide statistics per Client Session in releases 5.0 and greater."
  },
  "trpzClientSessClientSessionTableGroupRev2": {
    "name": "trpzClientSessClientSessionTableGroupRev2",
    "oid": "1.3.6.1.4.1.14525.4.4.1.2.2.6",
    "class": "objectgroup",
    "objects": [
      {
        "module": "TRAPEZE-NETWORKS-CLIENT-SESSION-MIB",
        "object": "trpzClSessClientSessSessionId"
      },
      {
        "module": "TRAPEZE-NETWORKS-CLIENT-SESSION-MIB",
        "object": "trpzClSessClientSessUsername"
      },
      {
        "module": "TRAPEZE-NETWORKS-CLIENT-SESSION-MIB",
        "object": "trpzClSessClientSessIpAddress"
      },
      {
        "module": "TRAPEZE-NETWORKS-CLIENT-SESSION-MIB",
        "object": "trpzClSessClientSessEncryptionType"
      },
      {
        "module": "TRAPEZE-NETWORKS-CLIENT-SESSION-MIB",
        "object": "trpzClSessClientSessVlan"
      },
      {
        "module": "TRAPEZE-NETWORKS-CLIENT-SESSION-MIB",
        "object": "trpzClSessClientSessApSerialNum"
      },
      {
        "module": "TRAPEZE-NETWORKS-CLIENT-SESSION-MIB",
        "object": "trpzClSessClientSessRadioNum"
      },
      {
        "module": "TRAPEZE-NETWORKS-CLIENT-SESSION-MIB",
        "object": "trpzClSessClientSessAuthServer"
      },
      {
        "module": "TRAPEZE-NETWORKS-CLIENT-SESSION-MIB",
        "object": "trpzClSessClientSessVlanTag"
      },
      {
        "module": "TRAPEZE-NETWORKS-CLIENT-SESSION-MIB",
        "object": "trpzClSessClientSessTimeStamp"
      },
      {
        "module": "TRAPEZE-NETWORKS-CLIENT-SESSION-MIB",
        "object": "trpzClSessClientSessSsid"
      },
      {
        "module": "TRAPEZE-NETWORKS-CLIENT-SESSION-MIB",
        "object": "trpzClSessClientSessLoginType"
      },
      {
        "module": "TRAPEZE-NETWORKS-CLIENT-SESSION-MIB",
        "object": "trpzClSessClientSessDot1xAuthMethod"
      },
      {
        "module": "TRAPEZE-NETWORKS-CLIENT-SESSION-MIB",
        "object": "trpzClSessClientSessSessionState"
      },
      {
        "module": "TRAPEZE-NETWORKS-CLIENT-SESSION-MIB",
        "object": "trpzClSessClientSessAccessMode"
      },
      {
        "module": "TRAPEZE-NETWORKS-CLIENT-SESSION-MIB",
        "object": "trpzClSessClientSessApNum"
      },
      {
        "module": "TRAPEZE-NETWORKS-CLIENT-SESSION-MIB",
        "object": "trpzClSessClientSessPhysPortNum"
      }
    ],
    "status": "obsolete",
    "description": "Group of columnar objects implemented to provide Client Session info in releases 6.2 to 7.7."
  },
  "trpzClientSessRoamingHistoryTableGroupRev2": {
    "name": "trpzClientSessRoamingHistoryTableGroupRev2",
    "oid": "1.3.6.1.4.1.14525.4.4.1.2.2.7",
    "class": "objectgroup",
    "objects": [
      {
        "module": "TRAPEZE-NETWORKS-CLIENT-SESSION-MIB",
        "object": "trpzClSessRoamHistApSerialNum"
      },
      {
        "module": "TRAPEZE-NETWORKS-CLIENT-SESSION-MIB",
        "object": "trpzClSessRoamHistRadioNum"
      },
      {
        "module": "TRAPEZE-NETWORKS-CLIENT-SESSION-MIB",
        "object": "trpzClSessRoamHistIpAddress"
      },
      {
        "module": "TRAPEZE-NETWORKS-CLIENT-SESSION-MIB",
        "object": "trpzClSessRoamHistTimeStamp"
      },
      {
        "module": "TRAPEZE-NETWORKS-CLIENT-SESSION-MIB",
        "object": "trpzClSessRoamHistAccessMode"
      },
      {
        "module": "TRAPEZE-NETWORKS-CLIENT-SESSION-MIB",
        "object": "trpzClSessRoamHistApNum"
      },
      {
        "module": "TRAPEZE-NETWORKS-CLIENT-SESSION-MIB",
        "object": "trpzClSessRoamHistPhysPortNum"
      }
    ],
    "status": "current",
    "description": "Group of columnar objects implemented to provide roaming history per Client Session in releases 6.2 and greater."
  },
  "trpzClSessClientAddressTableGroup": {
    "name": "trpzClSessClientAddressTableGroup",
    "oid": "1.3.6.1.4.1.14525.4.4.1.2.2.8",
    "class": "objectgroup",
    "objects": [
      {
        "module": "TRAPEZE-NETWORKS-CLIENT-SESSION-MIB",
        "object": "trpzClSessClientAddressType"
      },
      {
        "module": "TRAPEZE-NETWORKS-CLIENT-SESSION-MIB",
        "object": "trpzClSessClientAddressValue"
      }
    ],
    "status": "current",
    "description": "Group of columnar objects implemented to provide a complete listing of the clients' Internet addresses in releases 8.0 and greater."
  },
  "trpzClientSessClientSessionTableGroupRev3": {
    "name": "trpzClientSessClientSessionTableGroupRev3",
    "oid": "1.3.6.1.4.1.14525.4.4.1.2.2.9",
    "class": "objectgroup",
    "objects": [
      {
        "module": "TRAPEZE-NETWORKS-CLIENT-SESSION-MIB",
        "object": "trpzClSessClientSessSessionId"
      },
      {
        "module": "TRAPEZE-NETWORKS-CLIENT-SESSION-MIB",
        "object": "trpzClSessClientSessUsername"
      },
      {
        "module": "TRAPEZE-NETWORKS-CLIENT-SESSION-MIB",
        "object": "trpzClSessClientSessIpAddress"
      },
      {
        "module": "TRAPEZE-NETWORKS-CLIENT-SESSION-MIB",
        "object": "trpzClSessClientSessEncryptionType"
      },
      {
        "module": "TRAPEZE-NETWORKS-CLIENT-SESSION-MIB",
        "object": "trpzClSessClientSessVlan"
      },
      {
        "module": "TRAPEZE-NETWORKS-CLIENT-SESSION-MIB",
        "object": "trpzClSessClientSessApSerialNum"
      },
      {
        "module": "TRAPEZE-NETWORKS-CLIENT-SESSION-MIB",
        "object": "trpzClSessClientSessRadioNum"
      },
      {
        "module": "TRAPEZE-NETWORKS-CLIENT-SESSION-MIB",
        "object": "trpzClSessClientSessAuthServer"
      },
      {
        "module": "TRAPEZE-NETWORKS-CLIENT-SESSION-MIB",
        "object": "trpzClSessClientSessVlanTag"
      },
      {
        "module": "TRAPEZE-NETWORKS-CLIENT-SESSION-MIB",
        "object": "trpzClSessClientSessTimeStamp"
      },
      {
        "module": "TRAPEZE-NETWORKS-CLIENT-SESSION-MIB",
        "object": "trpzClSessClientSessSsid"
      },
      {
        "module": "TRAPEZE-NETWORKS-CLIENT-SESSION-MIB",
        "object": "trpzClSessClientSessLoginType"
      },
      {
        "module": "TRAPEZE-NETWORKS-CLIENT-SESSION-MIB",
        "object": "trpzClSessClientSessDot1xAuthMethod"
      },
      {
        "module": "TRAPEZE-NETWORKS-CLIENT-SESSION-MIB",
        "object": "trpzClSessClientSessSessionState"
      },
      {
        "module": "TRAPEZE-NETWORKS-CLIENT-SESSION-MIB",
        "object": "trpzClSessClientSessAccessMode"
      },
      {
        "module": "TRAPEZE-NETWORKS-CLIENT-SESSION-MIB",
        "object": "trpzClSessClientSessApNum"
      },
      {
        "module": "TRAPEZE-NETWORKS-CLIENT-SESSION-MIB",
        "object": "trpzClSessClientSessPhysPortNum"
      },
      {
        "module": "TRAPEZE-NETWORKS-CLIENT-SESSION-MIB",
        "object": "trpzClSessClientSessDeviceType"
      },
      {
        "module": "TRAPEZE-NETWORKS-CLIENT-SESSION-MIB",
        "object": "trpzClSessClientSessDeviceGroup"
      },
      {
        "module": "TRAPEZE-NETWORKS-CLIENT-SESSION-MIB",
        "object": "trpzClSessClientSessDeviceProfileName"
      }
    ],
    "status": "current",
    "description": "Group of columnar objects implemented to provide Client Session info in releases 8.0 and greater."
  },
  "meta": {
    "comments": [
      "ASN.1 source file:///Users/neermitt/kusanagi/mibs.snmplabs.com/asn1/TRAPEZE-NETWORKS-CLIENT-SESSION-MIB",
      "Produced by pysmi-0.3.4 at Fri May 24 22:13:53 2019",
      "On host NEERMITT-M-J0NV platform Darwin version 18.6.0 by user neermitt",
      "Using Python version 3.7.3 (default, Mar 27 2019, 09:23:15) "
    ],
    "module": "TRAPEZE-NETWORKS-CLIENT-SESSION-MIB"
  }
}